Workbook

Sheet Inputs
A1: Citizens Standard — Interactive Model Builder
A2: Adjust the yellow cells; everything else recalculates. Mode A = maximum wealth (deflation). Mode B = stable prices. Mode C = monthly dividend (inflation). See Mode Presets sheet for reference values.
A4: Mode preset
A5: Mode (A / B / C / custom) | B5: B
A6: Active configuration | B6: =IF(B5="A","Mode A — Maximum wealth via deflation",IF(B5="B","Mode B — Stable prices",IF(B5="C","Mode C — Monthly dividend",IF(B5="custom","Custom (manual values below)","⚠ Type A, B, C, or custom")))) -> Mode B — Stable prices
A7: Parameter | B7: Value | C7: Unit | D7: Notes
A8: Issuance channels (K-values)
A9: K1 — Citizenship endowment | B9: 0.025 | C9: % of GDP/capita per new citizen | D9: Mode A: 2.5%. Constitutional ceiling 5% (normal), 7.5% emergency.
A10: K2 — Growth dividend | B10: =IF($B$5="A",0.125,IF($B$5="B",0.84,IF($B$5="C",0.125,0.84))) -> 0.84
A11: K3 — Citizen dividend | B11: =IF($B$5="A",0,IF($B$5="B",0,IF($B$5="C",0.04,0))) -> 0 | C11: % of M2 issued annually as monthly dividend | D11: Mode A & B: 0%. Mode C: ~4% (calibrated to hit 2% inflation target).
A13: Macro environment
A14: Real GDP growth rate | B14: 0.02 | C14: annual | D14: Long-run US average ~2%. Drops in recessions.
A15: Population growth rate | B15: 0.005 | C15: annual | D15: US recent: 0.5%. Sets new-citizen K1 deposits.
A16: CPI inflation rate | B16: =IF($B$5="A",-0.016,IF($B$5="B",0,IF($B$5="C",0.02,0))) -> 0
A17: Equity index real return | B17: 0.065 | C17: annual | D17: Stable Floor compounds at this rate (after-inflation if CPI=0; nominal otherwise — see notes).
A19: Launch conditions (year 0)
A20: M2 money supply | B20: 22700000000000 | C20: dollars | D20: US M2 in launch year. Determines circulating pool size.
A21: Nominal GDP | B21: 30700000000000 | C21: dollars | D21: US GDP in launch year.
A22: Population | B22: 342000000 | C22: citizens | D22: Verified citizens at launch.
A23: Projection horizon | B23: 65 | C23: years | D23: Cohort tracked from age 0 to this age.
A24: Withdrawal rate at horizon | B24: 0.04 | C24: % of Stable Floor | D24: Conventional 4% safe withdrawal rate.

Sheet Projection
A1: Year-by-year simulation
A2: All values computed from Inputs. Black text = formulas. Do not edit.
A4: Year | B4: M2 ($) | C4: GDP ($) | D4: Population | E4: CPI index | F4: Births | G4: K1 total ($) | H4: K2 total ($) | I4: K3 total ($) | J4: K2 / citizen | K4: K3 monthly / citizen | L4: Cohort floor (nominal $) | M4: Cohort floor (real $) | N4: Cohort K3 cumulative (real $)
A5: 0 | B5: =Inputs!B20 -> 22700000000000 | C5: =Inputs!B21 -> 30700000000000 | D5: =Inputs!B22 -> 342000000 | E5: 1 | F5: =MAX(0,D5*Inputs!B15) -> 1710000 | G5: =Inputs!B9*(C5/D5)*F5 -> 3837500000 | H5: =Inputs!B10*C5*Inputs!B14 -> 515760000000 | I5: =Inputs!B11*B5 -> 0 | J5: =IF(D5>0,H5/D5,0) -> 1508.0702 | K5: =IF(D5>0,I5/D5/12,0) -> 0 | L5: =((G5/MAX(F5,1))+J5)*(1+Inputs!B17) -> 3996.1167 | M5: =L5/E5 -> 3996.1167 | N5: =K5*12/E5 -> 0
A6: 1 | B6: =B5+G5+H5+I5 -> 23219597500000 | C6: =C5*(1+Inputs!B14)*(1+Inputs!B16) -> 31314000000000 | D6: =D5*(1+Inputs!B15) -> 343710000 | E6: =E5*(1+Inputs!B16) -> 1 | F6: =MAX(0,D6*Inputs!B15) -> 1718550 | G6: =Inputs!B9*(C6/D6)*F6 -> 3914250000 | H6: =Inputs!B10*C6*Inputs!B14 -> 526075200000 | I6: =Inputs!B11*B6 -> 0 | J6: =IF(D6>0,H6/D6,0) -> 1530.5787 | K6: =IF(D6>0,I6/D6/12,0) -> 0 | L6: =(L5+J6)*(1+Inputs!B17) -> 5885.9306 | M6: =L6/E6 -> 5885.9306 | N6: =N5+K6*12/E6 -> 0
A7: 2 | B7: =B6+G6+H6+I6 -> 23749586950000 | C7: =C6*(1+Inputs!B14)*(1+Inputs!B16) -> 31940280000000 | D7: =D6*(1+Inputs!B15) -> 345428550 | E7: =E6*(1+Inputs!B16) -> 1 | F7: =MAX(0,D7*Inputs!B15) -> 1727142.8 | G7: =Inputs!B9*(C7/D7)*F7 -> 3992535000 | H7: =Inputs!B10*C7*Inputs!B14 -> 536596704000 | I7: =Inputs!B11*B7 -> 0 | J7: =IF(D7>0,H7/D7,0) -> 1553.4231 | K7: =IF(D7>0,I7/D7/12,0) -> 0 | L7: =(L6+J7)*(1+Inputs!B17) -> 7922.9117 | M7: =L7/E7 -> 7922.9117 | N7: =N6+K7*12/E7 -> 0
A8: 3 | B8: =B7+G7+H7+I7 -> 24290176189000 | C8: =C7*(1+Inputs!B14)*(1+Inputs!B16) -> 32579085600000 | D8: =D7*(1+Inputs!B15) -> 3.4715569e+08 | E8: =E7*(1+Inputs!B16) -> 1 | F8: =MAX(0,D8*Inputs!B15) -> 1735778.5 | G8: =Inputs!B9*(C8/D8)*F8 -> 4072385700 | H8: =Inputs!B10*C8*Inputs!B14 -> 547328638080 | I8: =Inputs!B11*B8 -> 0 | J8: =IF(D8>0,H8/D8,0) -> 1576.6086 | K8: =IF(D8>0,I8/D8/12,0) -> 0 | L8: =(L7+J8)*(1+Inputs!B17) -> 10116.989 | M8: =L8/E8 -> 10116.989 | N8: =N7+K8*12/E8 -> 0
A9: 4 | B9: =B8+G8+H8+I8 -> 24841577212780 | C9: =C8*(1+Inputs!B14)*(1+Inputs!B16) -> 33230667312000 | D9: =D8*(1+Inputs!B15) -> 3.4889147e+08 | E9: =E8*(1+Inputs!B16) -> 1 | F9: =MAX(0,D9*Inputs!B15) -> 1744457.4 | G9: =Inputs!B9*(C9/D9)*F9 -> 4153833414 | H9: =Inputs!B10*C9*Inputs!B14 -> 5.5827521e+11 | I9: =Inputs!B11*B9 -> 0 | J9: =IF(D9>0,H9/D9,0) -> 1600.14 | K9: =IF(D9>0,I9/D9/12,0) -> 0 | L9: =(L8+J9)*(1+Inputs!B17) -> 12478.742 | M9: =L9/E9 -> 12478.742 | N9: =N8+K9*12/E9 -> 0
A10: 5 | B10: =B9+G9+H9+I9 -> 2.5404006e+13 | C10: =C9*(1+Inputs!B14)*(1+Inputs!B16) -> 33895280658240 | D10: =D9*(1+Inputs!B15) -> 3.5063593e+08 | E10: =E9*(1+Inputs!B16) -> 1 | F10: =MAX(0,D10*Inputs!B15) -> 1753179.6 | G10: =Inputs!B9*(C10/D10)*F10 -> 4.2369101e+09 | H10: =Inputs!B10*C10*Inputs!B14 -> 5.6944072e+11 | I10: =Inputs!B11*B10 -> 0 | J10: =IF(D10>0,H10/D10,0) -> 1624.0227 | K10: =IF(D10>0,I10/D10/12,0) -> 0 | L10: =(L9+J10)*(1+Inputs!B17) -> 15019.445 | M10: =L10/E10 -> 15019.445 | N10: =N9+K10*12/E10 -> 0
A11: 6 | B11: =B10+G10+H10+I10 -> 2.5977684e+13 | C11: =C10*(1+Inputs!B14)*(1+Inputs!B16) -> 3.4573186e+13 | D11: =D10*(1+Inputs!B15) -> 3.5238911e+08 | E11: =E10*(1+Inputs!B16) -> 1 | F11: =MAX(0,D11*Inputs!B15) -> 1761945.5 | G11: =Inputs!B9*(C11/D11)*F11 -> 4.3216483e+09 | H11: =Inputs!B10*C11*Inputs!B14 -> 5.8082953e+11 | I11: =Inputs!B11*B11 -> 0 | J11: =IF(D11>0,H11/D11,0) -> 1648.2619 | K11: =IF(D11>0,I11/D11/12,0) -> 0 | L11: =(L10+J11)*(1+Inputs!B17) -> 17751.108 | M11: =L11/E11 -> 17751.108 | N11: =N10+K11*12/E11 -> 0
A12: 7 | B12: =B11+G11+H11+I11 -> 2.6562835e+13 | C12: =C11*(1+Inputs!B14)*(1+Inputs!B16) -> 3.526465e+13 | D12: =D11*(1+Inputs!B15) -> 3.5415105e+08 | E12: =E11*(1+Inputs!B16) -> 1 | F12: =MAX(0,D12*Inputs!B15) -> 1770755.3 | G12: =Inputs!B9*(C12/D12)*F12 -> 4.4080812e+09 | H12: =Inputs!B10*C12*Inputs!B14 -> 5.9244612e+11 | I12: =Inputs!B11*B12 -> 0 | J12: =IF(D12>0,H12/D12,0) -> 1672.8628 | K12: =IF(D12>0,I12/D12/12,0) -> 0 | L12: =(L11+J12)*(1+Inputs!B17) -> 20686.529 | M12: =L12/E12 -> 20686.529 | N12: =N11+K12*12/E12 -> 0
A13: 8 | B13: =B12+G12+H12+I12 -> 2.7159689e+13 | C13: =C12*(1+Inputs!B14)*(1+Inputs!B16) -> 3.5969943e+13 | D13: =D12*(1+Inputs!B15) -> 3.5592181e+08 | E13: =E12*(1+Inputs!B16) -> 1 | F13: =MAX(0,D13*Inputs!B15) -> 1779609 | G13: =Inputs!B9*(C13/D13)*F13 -> 4.4962429e+09 | H13: =Inputs!B10*C13*Inputs!B14 -> 6.0429504e+11 | I13: =Inputs!B11*B13 -> 0 | J13: =IF(D13>0,H13/D13,0) -> 1697.8309 | K13: =IF(D13>0,I13/D13/12,0) -> 0 | L13: =(L12+J13)*(1+Inputs!B17) -> 23839.343 | M13: =L13/E13 -> 23839.343 | N13: =N12+K13*12/E13 -> 0
A14: 9 | B14: =B13+G13+H13+I13 -> 2.7768481e+13 | C14: =C13*(1+Inputs!B14)*(1+Inputs!B16) -> 3.6689342e+13 | D14: =D13*(1+Inputs!B15) -> 3.5770142e+08 | E14: =E13*(1+Inputs!B16) -> 1 | F14: =MAX(0,D14*Inputs!B15) -> 1788507.1 | G14: =Inputs!B9*(C14/D14)*F14 -> 4.5861677e+09 | H14: =Inputs!B10*C14*Inputs!B14 -> 6.1638094e+11 | I14: =Inputs!B11*B14 -> 0 | J14: =IF(D14>0,H14/D14,0) -> 1723.1717 | K14: =IF(D14>0,I14/D14/12,0) -> 0 | L14: =(L13+J14)*(1+Inputs!B17) -> 27224.078 | M14: =L14/E14 -> 27224.078 | N14: =N13+K14*12/E14 -> 0
A15: 10 | B15: =B14+G14+H14+I14 -> 2.8389448e+13 | C15: =C14*(1+Inputs!B14)*(1+Inputs!B16) -> 3.7423129e+13 | D15: =D14*(1+Inputs!B15) -> 3.5948993e+08 | E15: =E14*(1+Inputs!B16) -> 1 | F15: =MAX(0,D15*Inputs!B15) -> 1797449.6 | G15: =Inputs!B9*(C15/D15)*F15 -> 4.6778911e+09 | H15: =Inputs!B10*C15*Inputs!B14 -> 6.2870856e+11 | I15: =Inputs!B11*B15 -> 0 | J15: =IF(D15>0,H15/D15,0) -> 1748.8906 | K15: =IF(D15>0,I15/D15/12,0) -> 0 | L15: =(L14+J15)*(1+Inputs!B17) -> 30856.212 | M15: =L15/E15 -> 30856.212 | N15: =N14+K15*12/E15 -> 0
A16: 11 | B16: =B15+G15+H15+I15 -> 2.9022834e+13 | C16: =C15*(1+Inputs!B14)*(1+Inputs!B16) -> 3.8171591e+13 | D16: =D15*(1+Inputs!B15) -> 3.6128737e+08 | E16: =E15*(1+Inputs!B16) -> 1 | F16: =MAX(0,D16*Inputs!B15) -> 1806436.9 | G16: =Inputs!B9*(C16/D16)*F16 -> 4.7714489e+09 | H16: =Inputs!B10*C16*Inputs!B14 -> 6.4128273e+11 | I16: =Inputs!B11*B16 -> 0 | J16: =IF(D16>0,H16/D16,0) -> 1774.9935 | K16: =IF(D16>0,I16/D16/12,0) -> 0 | L16: =(L15+J16)*(1+Inputs!B17) -> 34752.233 | M16: =L16/E16 -> 34752.233 | N16: =N15+K16*12/E16 -> 0
A17: 12 | B17: =B16+G16+H16+I16 -> 2.9668888e+13 | C17: =C16*(1+Inputs!B14)*(1+Inputs!B16) -> 3.8935023e+13 | D17: =D16*(1+Inputs!B15) -> 3.6309381e+08 | E17: =E16*(1+Inputs!B16) -> 1 | F17: =MAX(0,D17*Inputs!B15) -> 1815469.1 | G17: =Inputs!B9*(C17/D17)*F17 -> 4.8668779e+09 | H17: =Inputs!B10*C17*Inputs!B14 -> 6.5410839e+11 | I17: =Inputs!B11*B17 -> 0 | J17: =IF(D17>0,H17/D17,0) -> 1801.4859 | K17: =IF(D17>0,I17/D17/12,0) -> 0 | L17: =(L16+J17)*(1+Inputs!B17) -> 38929.711 | M17: =L17/E17 -> 38929.711 | N17: =N16+K17*12/E17 -> 0
A18: 13 | B18: =B17+G17+H17+I17 -> 3.0327864e+13 | C18: =C17*(1+Inputs!B14)*(1+Inputs!B16) -> 3.9713724e+13 | D18: =D17*(1+Inputs!B15) -> 3.6490928e+08 | E18: =E17*(1+Inputs!B16) -> 1 | F18: =MAX(0,D18*Inputs!B15) -> 1824546.4 | G18: =Inputs!B9*(C18/D18)*F18 -> 4.9642154e+09 | H18: =Inputs!B10*C18*Inputs!B14 -> 6.6719056e+11 | I18: =Inputs!B11*B18 -> 0 | J18: =IF(D18>0,H18/D18,0) -> 1828.3738 | K18: =IF(D18>0,I18/D18/12,0) -> 0 | L18: =(L17+J18)*(1+Inputs!B17) -> 43407.36 | M18: =L18/E18 -> 43407.36 | N18: =N17+K18*12/E18 -> 0
A19: 14 | B19: =B18+G18+H18+I18 -> 3.1000018e+13 | C19: =C18*(1+Inputs!B14)*(1+Inputs!B16) -> 4.0507998e+13 | D19: =D18*(1+Inputs!B15) -> 3.6673383e+08 | E19: =E18*(1+Inputs!B16) -> 1 | F19: =MAX(0,D19*Inputs!B15) -> 1833669.1 | G19: =Inputs!B9*(C19/D19)*F19 -> 5.0634998e+09 | H19: =Inputs!B10*C19*Inputs!B14 -> 6.8053437e+11 | I19: =Inputs!B11*B19 -> 0 | J19: =IF(D19>0,H19/D19,0) -> 1855.6629 | K19: =IF(D19>0,I19/D19/12,0) -> 0 | L19: =(L18+J19)*(1+Inputs!B17) -> 48205.12 | M19: =L19/E19 -> 48205.12 | N19: =N18+K19*12/E19 -> 0
A20: 15 | B20: =B19+G19+H19+I19 -> 3.1685616e+13 | C20: =C19*(1+Inputs!B14)*(1+Inputs!B16) -> 4.1318158e+13 | D20: =D19*(1+Inputs!B15) -> 3.685675e+08 | E20: =E19*(1+Inputs!B16) -> 1 | F20: =MAX(0,D20*Inputs!B15) -> 1842837.5 | G20: =Inputs!B9*(C20/D20)*F20 -> 5.1647697e+09 | H20: =Inputs!B10*C20*Inputs!B14 -> 6.9414505e+11 | I20: =Inputs!B11*B20 -> 0 | J20: =IF(D20>0,H20/D20,0) -> 1883.3594 | K20: =IF(D20>0,I20/D20/12,0) -> 0 | L20: =(L19+J20)*(1+Inputs!B17) -> 53344.23 | M20: =L20/E20 -> 53344.23 | N20: =N19+K20*12/E20 -> 0
A21: 16 | B21: =B20+G20+H20+I20 -> 32384926020041 | C21: =C20*(1+Inputs!B14)*(1+Inputs!B16) -> 4.2144521e+13 | D21: =D20*(1+Inputs!B15) -> 3.7041033e+08 | E21: =E20*(1+Inputs!B16) -> 1 | F21: =MAX(0,D21*Inputs!B15) -> 1852051.7 | G21: =Inputs!B9*(C21/D21)*F21 -> 5.2680651e+09 | H21: =Inputs!B10*C21*Inputs!B14 -> 7.0802796e+11 | I21: =Inputs!B11*B21 -> 0 | J21: =IF(D21>0,H21/D21,0) -> 1911.4692 | K21: =IF(D21>0,I21/D21/12,0) -> 0 | L21: =(L20+J21)*(1+Inputs!B17) -> 58847.32 | M21: =L21/E21 -> 58847.32 | N21: =N20+K21*12/E21 -> 0
A22: 17 | B22: =B21+G21+H21+I21 -> 3.3098222e+13 | C22: =C21*(1+Inputs!B14)*(1+Inputs!B16) -> 4.2987412e+13 | D22: =D21*(1+Inputs!B15) -> 3.7226239e+08 | E22: =E21*(1+Inputs!B16) -> 1 | F22: =MAX(0,D22*Inputs!B15) -> 1861311.9 | G22: =Inputs!B9*(C22/D22)*F22 -> 5.3734264e+09 | H22: =Inputs!B10*C22*Inputs!B14 -> 7.2218851e+11 | I22: =Inputs!B11*B22 -> 0 | J22: =IF(D22>0,H22/D22,0) -> 1939.9986 | K22: =IF(D22>0,I22/D22/12,0) -> 0 | L22: =(L21+J22)*(1+Inputs!B17) -> 64738.494 | M22: =L22/E22 -> 64738.494 | N22: =N21+K22*12/E22 -> 0
A23: 18 | B23: =B22+G22+H22+I22 -> 3.3825784e+13 | C23: =C22*(1+Inputs!B14)*(1+Inputs!B16) -> 4.384716e+13 | D23: =D22*(1+Inputs!B15) -> 3.741237e+08 | E23: =E22*(1+Inputs!B16) -> 1 | F23: =MAX(0,D23*Inputs!B15) -> 1870618.5 | G23: =Inputs!B9*(C23/D23)*F23 -> 5.480895e+09 | H23: =Inputs!B10*C23*Inputs!B14 -> 7.3663228e+11 | I23: =Inputs!B11*B23 -> 0 | J23: =IF(D23>0,H23/D23,0) -> 1968.9538 | K23: =IF(D23>0,I23/D23/12,0) -> 0 | L23: =(L22+J23)*(1+Inputs!B17) -> 71043.432 | M23: =L23/E23 -> 71043.432 | N23: =N22+K23*12/E23 -> 0
A24: 19 | B24: =B23+G23+H23+I23 -> 3.4567897e+13 | C24: =C23*(1+Inputs!B14)*(1+Inputs!B16) -> 4.4724103e+13 | D24: =D23*(1+Inputs!B15) -> 3.7599432e+08 | E24: =E23*(1+Inputs!B16) -> 1 | F24: =MAX(0,D24*Inputs!B15) -> 1879971.6 | G24: =Inputs!B9*(C24/D24)*F24 -> 5.5905129e+09 | H24: =Inputs!B10*C24*Inputs!B14 -> 7.5136493e+11 | I24: =Inputs!B11*B24 -> 0 | J24: =IF(D24>0,H24/D24,0) -> 1998.3412 | K24: =IF(D24>0,I24/D24/12,0) -> 0 | L24: =(L23+J24)*(1+Inputs!B17) -> 77789.489 | M24: =L24/E24 -> 77789.489 | N24: =N23+K24*12/E24 -> 0
A25: 20 | B25: =B24+G24+H24+I24 -> 3.5324853e+13 | C25: =C24*(1+Inputs!B14)*(1+Inputs!B16) -> 4.5618585e+13 | D25: =D24*(1+Inputs!B15) -> 3.7787429e+08 | E25: =E24*(1+Inputs!B16) -> 1 | F25: =MAX(0,D25*Inputs!B15) -> 1889371.4 | G25: =Inputs!B9*(C25/D25)*F25 -> 5.7023231e+09 | H25: =Inputs!B10*C25*Inputs!B14 -> 7.6639223e+11 | I25: =Inputs!B11*B25 -> 0 | J25: =IF(D25>0,H25/D25,0) -> 2028.1672 | K25: =IF(D25>0,I25/D25/12,0) -> 0 | L25: =(L24+J25)*(1+Inputs!B17) -> 85005.804 | M25: =L25/E25 -> 85005.804 | N25: =N24+K25*12/E25 -> 0
A26: 21 | B26: =B25+G25+H25+I25 -> 36096947156175 | C26: =C25*(1+Inputs!B14)*(1+Inputs!B16) -> 4.6530957e+13 | D26: =D25*(1+Inputs!B15) -> 3.7976366e+08 | E26: =E25*(1+Inputs!B16) -> 1 | F26: =MAX(0,D26*Inputs!B15) -> 1898818.3 | G26: =Inputs!B9*(C26/D26)*F26 -> 5.8163696e+09 | H26: =Inputs!B10*C26*Inputs!B14 -> 7.8172007e+11 | I26: =Inputs!B11*B26 -> 0 | J26: =IF(D26>0,H26/D26,0) -> 2058.4383 | K26: =IF(D26>0,I26/D26/12,0) -> 0 | L26: =(L25+J26)*(1+Inputs!B17) -> 92723.418 | M26: =L26/E26 -> 92723.418 | N26: =N25+K26*12/E26 -> 0
A27: 22 | B27: =B26+G26+H26+I26 -> 3.6884484e+13 | C27: =C26*(1+Inputs!B14)*(1+Inputs!B16) -> 4.7461576e+13 | D27: =D26*(1+Inputs!B15) -> 3.8166248e+08 | E27: =E26*(1+Inputs!B16) -> 1 | F27: =MAX(0,D27*Inputs!B15) -> 1908312.4 | G27: =Inputs!B9*(C27/D27)*F27 -> 5.932697e+09 | H27: =Inputs!B10*C27*Inputs!B14 -> 7.9735447e+11 | I27: =Inputs!B11*B27 -> 0 | J27: =IF(D27>0,H27/D27,0) -> 2089.1613 | K27: =IF(D27>0,I27/D27/12,0) -> 0 | L27: =(L26+J27)*(1+Inputs!B17) -> 100975.4 | M27: =L27/E27 -> 100975.4 | N27: =N26+K27*12/E27 -> 0
A28: 23 | B28: =B27+G27+H27+I27 -> 3.7687771e+13 | C28: =C27*(1+Inputs!B14)*(1+Inputs!B16) -> 4.8410807e+13 | D28: =D27*(1+Inputs!B15) -> 3.8357079e+08 | E28: =E27*(1+Inputs!B16) -> 1 | F28: =MAX(0,D28*Inputs!B15) -> 1917853.9 | G28: =Inputs!B9*(C28/D28)*F28 -> 6.0513509e+09 | H28: =Inputs!B10*C28*Inputs!B14 -> 8.1330156e+11 | I28: =Inputs!B11*B28 -> 0 | J28: =IF(D28>0,H28/D28,0) -> 2120.3428 | K28: =IF(D28>0,I28/D28/12,0) -> 0 | L28: =(L27+J28)*(1+Inputs!B17) -> 109796.96 | M28: =L28/E28 -> 109796.96 | N28: =N27+K28*12/E28 -> 0
A29: 24 | B29: =B28+G28+H28+I28 -> 3.8507124e+13 | C29: =C28*(1+Inputs!B14)*(1+Inputs!B16) -> 4.9379024e+13 | D29: =D28*(1+Inputs!B15) -> 3.8548864e+08 | E29: =E28*(1+Inputs!B16) -> 1 | F29: =MAX(0,D29*Inputs!B15) -> 1927443.2 | G29: =Inputs!B9*(C29/D29)*F29 -> 6.1723779e+09 | H29: =Inputs!B10*C29*Inputs!B14 -> 8.295676e+11 | I29: =Inputs!B11*B29 -> 0 | J29: =IF(D29>0,H29/D29,0) -> 2151.9897 | K29: =IF(D29>0,I29/D29/12,0) -> 0 | L29: =(L28+J29)*(1+Inputs!B17) -> 119225.63 | M29: =L29/E29 -> 119225.63 | N29: =N28+K29*12/E29 -> 0
A30: 25 | B30: =B29+G29+H29+I29 -> 3.9342864e+13 | C30: =C29*(1+Inputs!B14)*(1+Inputs!B16) -> 5.0366604e+13 | D30: =D29*(1+Inputs!B15) -> 3.8741609e+08 | E30: =E29*(1+Inputs!B16) -> 1 | F30: =MAX(0,D30*Inputs!B15) -> 1937080.4 | G30: =Inputs!B9*(C30/D30)*F30 -> 6.2958255e+09 | H30: =Inputs!B10*C30*Inputs!B14 -> 8.4615895e+11 | I30: =Inputs!B11*B30 -> 0 | J30: =IF(D30>0,H30/D30,0) -> 2184.109 | K30: =IF(D30>0,I30/D30/12,0) -> 0 | L30: =(L29+J30)*(1+Inputs!B17) -> 129301.38 | M30: =L30/E30 -> 129301.38 | N30: =N29+K30*12/E30 -> 0
A31: 26 | B31: =B30+G30+H30+I30 -> 4.0195318e+13 | C31: =C30*(1+Inputs!B14)*(1+Inputs!B16) -> 5.1373936e+13 | D31: =D30*(1+Inputs!B15) -> 3.8935317e+08 | E31: =E30*(1+Inputs!B16) -> 1 | F31: =MAX(0,D31*Inputs!B15) -> 1946765.8 | G31: =Inputs!B9*(C31/D31)*F31 -> 6.421742e+09 | H31: =Inputs!B10*C31*Inputs!B14 -> 8.6308213e+11 | I31: =Inputs!B11*B31 -> 0 | J31: =IF(D31>0,H31/D31,0) -> 2216.7076 | K31: =IF(D31>0,I31/D31/12,0) -> 0 | L31: =(L30+J31)*(1+Inputs!B17) -> 140066.76 | M31: =L31/E31 -> 140066.76 | N31: =N30+K31*12/E31 -> 0
A32: 27 | B32: =B31+G31+H31+I31 -> 4.1064822e+13 | C32: =C31*(1+Inputs!B14)*(1+Inputs!B16) -> 52401414832882 | D32: =D31*(1+Inputs!B15) -> 3.9129993e+08 | E32: =E31*(1+Inputs!B16) -> 1 | F32: =MAX(0,D32*Inputs!B15) -> 1956499.7 | G32: =Inputs!B9*(C32/D32)*F32 -> 6.5501769e+09 | H32: =Inputs!B10*C32*Inputs!B14 -> 8.8034377e+11 | I32: =Inputs!B11*B32 -> 0 | J32: =IF(D32>0,H32/D32,0) -> 2249.7928 | K32: =IF(D32>0,I32/D32/12,0) -> 0 | L32: =(L31+J32)*(1+Inputs!B17) -> 151567.13 | M32: =L32/E32 -> 151567.13 | N32: =N31+K32*12/E32 -> 0
A33: 28 | B33: =B32+G32+H32+I32 -> 4.1951716e+13 | C33: =C32*(1+Inputs!B14)*(1+Inputs!B16) -> 5.3449443e+13 | D33: =D32*(1+Inputs!B15) -> 3.9325643e+08 | E33: =E32*(1+Inputs!B16) -> 1 | F33: =MAX(0,D33*Inputs!B15) -> 1966282.2 | G33: =Inputs!B9*(C33/D33)*F33 -> 6.6811804e+09 | H33: =Inputs!B10*C33*Inputs!B14 -> 8.9795064e+11 | I33: =Inputs!B11*B33 -> 0 | J33: =IF(D33>0,H33/D33,0) -> 2283.3718 | K33: =IF(D33>0,I33/D33/12,0) -> 0 | L33: =(L32+J33)*(1+Inputs!B17) -> 163850.78 | M33: =L33/E33 -> 163850.78 | N33: =N32+K33*12/E33 -> 0
A34: 29 | B34: =B33+G33+H33+I33 -> 4.2856348e+13 | C34: =C33*(1+Inputs!B14)*(1+Inputs!B16) -> 5.4518432e+13 | D34: =D33*(1+Inputs!B15) -> 3.9522271e+08 | E34: =E33*(1+Inputs!B16) -> 1 | F34: =MAX(0,D34*Inputs!B15) -> 1976113.6 | G34: =Inputs!B9*(C34/D34)*F34 -> 6.814804e+09 | H34: =Inputs!B10*C34*Inputs!B14 -> 9.1590966e+11 | I34: =Inputs!B11*B34 -> 0 | J34: =IF(D34>0,H34/D34,0) -> 2317.452 | K34: =IF(D34>0,I34/D34/12,0) -> 0 | L34: =(L33+J34)*(1+Inputs!B17) -> 176969.17 | M34: =L34/E34 -> 176969.17 | N34: =N33+K34*12/E34 -> 0
A35: 30 | B35: =B34+G34+H34+I34 -> 4.3779073e+13 | C35: =C34*(1+Inputs!B14)*(1+Inputs!B16) -> 55608800631973 | D35: =D34*(1+Inputs!B15) -> 3.9719883e+08 | E35: =E34*(1+Inputs!B16) -> 1 | F35: =MAX(0,D35*Inputs!B15) -> 1985994.1 | G35: =Inputs!B9*(C35/D35)*F35 -> 6.9511001e+09 | H35: =Inputs!B10*C35*Inputs!B14 -> 9.3422785e+11 | I35: =Inputs!B11*B35 -> 0 | J35: =IF(D35>0,H35/D35,0) -> 2352.0408 | K35: =IF(D35>0,I35/D35/12,0) -> 0 | L35: =(L34+J35)*(1+Inputs!B17) -> 190977.09 | M35: =L35/E35 -> 190977.09 | N35: =N34+K35*12/E35 -> 0
A36: 31 | B36: =B35+G35+H35+I35 -> 4.4720251e+13 | C36: =C35*(1+Inputs!B14)*(1+Inputs!B16) -> 5.6720977e+13 | D36: =D35*(1+Inputs!B15) -> 3.9918482e+08 | E36: =E35*(1+Inputs!B16) -> 1 | F36: =MAX(0,D36*Inputs!B15) -> 1995924.1 | G36: =Inputs!B9*(C36/D36)*F36 -> 7.0901221e+09 | H36: =Inputs!B10*C36*Inputs!B14 -> 9.5291241e+11 | I36: =Inputs!B11*B36 -> 0 | J36: =IF(D36>0,H36/D36,0) -> 2387.1459 | K36: =IF(D36>0,I36/D36/12,0) -> 0 | L36: =(L35+J36)*(1+Inputs!B17) -> 205932.91 | M36: =L36/E36 -> 205932.91 | N36: =N35+K36*12/E36 -> 0
A37: 32 | B37: =B36+G36+H36+I36 -> 4.5680254e+13 | C37: =C36*(1+Inputs!B14)*(1+Inputs!B16) -> 5.7855396e+13 | D37: =D36*(1+Inputs!B15) -> 4.0118075e+08 | E37: =E36*(1+Inputs!B16) -> 1 | F37: =MAX(0,D37*Inputs!B15) -> 2005903.7 | G37: =Inputs!B9*(C37/D37)*F37 -> 7.2319245e+09 | H37: =Inputs!B10*C37*Inputs!B14 -> 9.7197066e+11 | I37: =Inputs!B11*B37 -> 0 | J37: =IF(D37>0,H37/D37,0) -> 2422.7749 | K37: =IF(D37>0,I37/D37/12,0) -> 0 | L37: =(L36+J37)*(1+Inputs!B17) -> 221898.8 | M37: =L37/E37 -> 221898.8 | N37: =N36+K37*12/E37 -> 0
A38: 33 | B38: =B37+G37+H37+I37 -> 4.6659457e+13 | C38: =C37*(1+Inputs!B14)*(1+Inputs!B16) -> 5.9012504e+13 | D38: =D37*(1+Inputs!B15) -> 4.0318665e+08 | E38: =E37*(1+Inputs!B16) -> 1 | F38: =MAX(0,D38*Inputs!B15) -> 2015933.3 | G38: =Inputs!B9*(C38/D38)*F38 -> 7.376563e+09 | H38: =Inputs!B10*C38*Inputs!B14 -> 9.9141007e+11 | I38: =Inputs!B11*B38 -> 0 | J38: =IF(D38>0,H38/D38,0) -> 2458.9358 | K38: =IF(D38>0,I38/D38/12,0) -> 0 | L38: =(L37+J38)*(1+Inputs!B17) -> 238940.99 | M38: =L38/E38 -> 238940.99 | N38: =N37+K38*12/E38 -> 0
A39: 34 | B39: =B38+G38+H38+I38 -> 47658243227428 | C39: =C38*(1+Inputs!B14)*(1+Inputs!B16) -> 6.0192754e+13 | D39: =D38*(1+Inputs!B15) -> 4.0520258e+08 | E39: =E38*(1+Inputs!B16) -> 1 | F39: =MAX(0,D39*Inputs!B15) -> 2026012.9 | G39: =Inputs!B9*(C39/D39)*F39 -> 7.5240943e+09 | H39: =Inputs!B10*C39*Inputs!B14 -> 1.0112383e+12 | I39: =Inputs!B11*B39 -> 0 | J39: =IF(D39>0,H39/D39,0) -> 2495.6363 | K39: =IF(D39>0,I39/D39/12,0) -> 0 | L39: =(L38+J39)*(1+Inputs!B17) -> 257130.01 | M39: =L39/E39 -> 257130.01 | N39: =N38+K39*12/E39 -> 0
A40: 35 | B40: =B39+G39+H39+I39 -> 4.8677006e+13 | C40: =C39*(1+Inputs!B14)*(1+Inputs!B16) -> 6.1396609e+13 | D40: =D39*(1+Inputs!B15) -> 4.072286e+08 | E40: =E39*(1+Inputs!B16) -> 1 | F40: =MAX(0,D40*Inputs!B15) -> 2036143 | G40: =Inputs!B9*(C40/D40)*F40 -> 7.6745762e+09 | H40: =Inputs!B10*C40*Inputs!B14 -> 1.031463e+12 | I40: =Inputs!B11*B40 -> 0 | J40: =IF(D40>0,H40/D40,0) -> 2532.8846 | K40: =IF(D40>0,I40/D40/12,0) -> 0 | L40: =(L39+J40)*(1+Inputs!B17) -> 276540.98 | M40: =L40/E40 -> 276540.98 | N40: =N39+K40*12/E40 -> 0
A41: 36 | B41: =B40+G40+H40+I40 -> 4.9716143e+13 | C41: =C40*(1+Inputs!B14)*(1+Inputs!B16) -> 6.2624541e+13 | D41: =D40*(1+Inputs!B15) -> 4.0926474e+08 | E41: =E40*(1+Inputs!B16) -> 1 | F41: =MAX(0,D41*Inputs!B15) -> 2046323.7 | G41: =Inputs!B9*(C41/D41)*F41 -> 7.8280677e+09 | H41: =Inputs!B10*C41*Inputs!B14 -> 1.0520923e+12 | I41: =Inputs!B11*B41 -> 0 | J41: =IF(D41>0,H41/D41,0) -> 2570.6888 | K41: =IF(D41>0,I41/D41/12,0) -> 0 | L41: =(L40+J41)*(1+Inputs!B17) -> 297253.93 | M41: =L41/E41 -> 297253.93 | N41: =N40+K41*12/E41 -> 0
A42: 37 | B42: =B41+G41+H41+I41 -> 5.0776064e+13 | C42: =C41*(1+Inputs!B14)*(1+Inputs!B16) -> 6.3877032e+13 | D42: =D41*(1+Inputs!B15) -> 4.1131106e+08 | E42: =E41*(1+Inputs!B16) -> 1 | F42: =MAX(0,D42*Inputs!B15) -> 2056555.3 | G42: =Inputs!B9*(C42/D42)*F42 -> 7.984629e+09 | H42: =Inputs!B10*C42*Inputs!B14 -> 1.0731341e+12 | I42: =Inputs!B11*B42 -> 0 | J42: =IF(D42>0,H42/D42,0) -> 2609.0573 | K42: =IF(D42>0,I42/D42/12,0) -> 0 | L42: =(L41+J42)*(1+Inputs!B17) -> 319354.08 | M42: =L42/E42 -> 319354.08 | N42: =N41+K42*12/E42 -> 0
A43: 38 | B43: =B42+G42+H42+I42 -> 5.1857182e+13 | C43: =C42*(1+Inputs!B14)*(1+Inputs!B16) -> 6.5154573e+13 | D43: =D42*(1+Inputs!B15) -> 4.1336762e+08 | E43: =E42*(1+Inputs!B16) -> 1 | F43: =MAX(0,D43*Inputs!B15) -> 2066838.1 | G43: =Inputs!B9*(C43/D43)*F43 -> 8.1443216e+09 | H43: =Inputs!B10*C43*Inputs!B14 -> 1.0945968e+12 | I43: =Inputs!B11*B43 -> 0 | J43: =IF(D43>0,H43/D43,0) -> 2647.9985 | K43: =IF(D43>0,I43/D43/12,0) -> 0 | L43: =(L42+J43)*(1+Inputs!B17) -> 342932.22 | M43: =L43/E43 -> 342932.22 | N43: =N42+K43*12/E43 -> 0
A44: 39 | B44: =B43+G43+H43+I43 -> 5.2959923e+13 | C44: =C43*(1+Inputs!B14)*(1+Inputs!B16) -> 6.6457664e+13 | D44: =D43*(1+Inputs!B15) -> 4.1543446e+08 | E44: =E43*(1+Inputs!B16) -> 1 | F44: =MAX(0,D44*Inputs!B15) -> 2077172.3 | G44: =Inputs!B9*(C44/D44)*F44 -> 8.307208e+09 | H44: =Inputs!B10*C44*Inputs!B14 -> 1.1164888e+12 | I44: =Inputs!B11*B44 -> 0 | J44: =IF(D44>0,H44/D44,0) -> 2687.5208 | K44: =IF(D44>0,I44/D44/12,0) -> 0 | L44: =(L43+J44)*(1+Inputs!B17) -> 368085.02 | M44: =L44/E44 -> 368085.02 | N44: =N43+K44*12/E44 -> 0
A45: 40 | B45: =B44+G44+H44+I44 -> 54084719455756 | C45: =C44*(1+Inputs!B14)*(1+Inputs!B16) -> 67786817672976 | D45: =D44*(1+Inputs!B15) -> 4.1751163e+08 | E45: =E44*(1+Inputs!B16) -> 1 | F45: =MAX(0,D45*Inputs!B15) -> 2087558.1 | G45: =Inputs!B9*(C45/D45)*F45 -> 8.4733522e+09 | H45: =Inputs!B10*C45*Inputs!B14 -> 1138818536906 | I45: =Inputs!B11*B45 -> 0 | J45: =IF(D45>0,H45/D45,0) -> 2727.6331 | K45: =IF(D45>0,I45/D45/12,0) -> 0 | L45: =(L44+J45)*(1+Inputs!B17) -> 394915.48 | M45: =L45/E45 -> 394915.48 | N45: =N44+K45*12/E45 -> 0
A46: 41 | B46: =B45+G45+H45+I45 -> 5.5232011e+13 | C46: =C45*(1+Inputs!B14)*(1+Inputs!B16) -> 6.9142554e+13 | D46: =D45*(1+Inputs!B15) -> 4.1959919e+08 | E46: =E45*(1+Inputs!B16) -> 1 | F46: =MAX(0,D46*Inputs!B15) -> 2097995.9 | G46: =Inputs!B9*(C46/D46)*F46 -> 8.6428193e+09 | H46: =Inputs!B10*C46*Inputs!B14 -> 1.1615949e+12 | I46: =Inputs!B11*B46 -> 0 | J46: =IF(D46>0,H46/D46,0) -> 2768.344 | K46: =IF(D46>0,I46/D46/12,0) -> 0 | L46: =(L45+J46)*(1+Inputs!B17) -> 423533.27 | M46: =L46/E46 -> 423533.27 | N46: =N45+K46*12/E46 -> 0
A47: 42 | B47: =B46+G46+H46+I46 -> 5.6402249e+13 | C47: =C46*(1+Inputs!B14)*(1+Inputs!B16) -> 7.0525405e+13 | D47: =D46*(1+Inputs!B15) -> 4.2169718e+08 | E47: =E46*(1+Inputs!B16) -> 1 | F47: =MAX(0,D47*Inputs!B15) -> 2108485.9 | G47: =Inputs!B9*(C47/D47)*F47 -> 8.8156756e+09 | H47: =Inputs!B10*C47*Inputs!B14 -> 1184826805797 | I47: =Inputs!B11*B47 -> 0 | J47: =IF(D47>0,H47/D47,0) -> 2809.6626 | K47: =IF(D47>0,I47/D47/12,0) -> 0 | L47: =(L46+J47)*(1+Inputs!B17) -> 454055.22 | M47: =L47/E47 -> 454055.22 | N47: =N46+K47*12/E47 -> 0
A48: 43 | B48: =B47+G47+H47+I47 -> 5.7595892e+13 | C48: =C47*(1+Inputs!B14)*(1+Inputs!B16) -> 7.1935913e+13 | D48: =D47*(1+Inputs!B15) -> 4.2380567e+08 | E48: =E47*(1+Inputs!B16) -> 1 | F48: =MAX(0,D48*Inputs!B15) -> 2119028.3 | G48: =Inputs!B9*(C48/D48)*F48 -> 8.9919892e+09 | H48: =Inputs!B10*C48*Inputs!B14 -> 1.2085233e+12 | I48: =Inputs!B11*B48 -> 0 | J48: =IF(D48>0,H48/D48,0) -> 2851.5979 | K48: =IF(D48>0,I48/D48/12,0) -> 0 | L48: =(L47+J48)*(1+Inputs!B17) -> 486605.76 | M48: =L48/E48 -> 486605.76 | N48: =N47+K48*12/E48 -> 0
A49: 44 | B49: =B48+G48+H48+I48 -> 58813406884268 | C49: =C48*(1+Inputs!B14)*(1+Inputs!B16) -> 7.3374631e+13 | D49: =D48*(1+Inputs!B15) -> 4.259247e+08 | E49: =E48*(1+Inputs!B16) -> 1 | F49: =MAX(0,D49*Inputs!B15) -> 2129623.5 | G49: =Inputs!B9*(C49/D49)*F49 -> 9.1718289e+09 | H49: =Inputs!B10*C49*Inputs!B14 -> 1.2326938e+12 | I49: =Inputs!B11*B49 -> 0 | J49: =IF(D49>0,H49/D49,0) -> 2894.159 | K49: =IF(D49>0,I49/D49/12,0) -> 0 | L49: =(L48+J49)*(1+Inputs!B17) -> 521317.42 | M49: =L49/E49 -> 521317.42 | N49: =N48+K49*12/E49 -> 0
A50: 45 | B50: =B49+G49+H49+I49 -> 6.0055273e+13 | C50: =C49*(1+Inputs!B14)*(1+Inputs!B16) -> 7.4842124e+13 | D50: =D49*(1+Inputs!B15) -> 4.2805432e+08 | E50: =E49*(1+Inputs!B16) -> 1 | F50: =MAX(0,D50*Inputs!B15) -> 2140271.6 | G50: =Inputs!B9*(C50/D50)*F50 -> 9.3552655e+09 | H50: =Inputs!B10*C50*Inputs!B14 -> 1.2573477e+12 | I50: =Inputs!B11*B50 -> 0 | J50: =IF(D50>0,H50/D50,0) -> 2937.3554 | K50: =IF(D50>0,I50/D50/12,0) -> 0 | L50: =(L49+J50)*(1+Inputs!B17) -> 558331.33 | M50: =L50/E50 -> 558331.33 | N50: =N49+K50*12/E50 -> 0
A51: 46 | B51: =B50+G50+H50+I50 -> 6.1321975e+13 | C51: =C50*(1+Inputs!B14)*(1+Inputs!B16) -> 7.6338967e+13 | D51: =D50*(1+Inputs!B15) -> 4.3019459e+08 | E51: =E50*(1+Inputs!B16) -> 1 | F51: =MAX(0,D51*Inputs!B15) -> 2150973 | G51: =Inputs!B9*(C51/D51)*F51 -> 9.5423708e+09 | H51: =Inputs!B10*C51*Inputs!B14 -> 1.2824946e+12 | I51: =Inputs!B11*B51 -> 0 | J51: =IF(D51>0,H51/D51,0) -> 2981.1966 | K51: =IF(D51>0,I51/D51/12,0) -> 0 | L51: =(L50+J51)*(1+Inputs!B17) -> 597797.84 | M51: =L51/E51 -> 597797.84 | N51: =N50+K51*12/E51 -> 0
A52: 47 | B52: =B51+G51+H51+I51 -> 6.2614012e+13 | C52: =C51*(1+Inputs!B14)*(1+Inputs!B16) -> 7.7865746e+13 | D52: =D51*(1+Inputs!B15) -> 4.3234557e+08 | E52: =E51*(1+Inputs!B16) -> 1 | F52: =MAX(0,D52*Inputs!B15) -> 2161727.8 | G52: =Inputs!B9*(C52/D52)*F52 -> 9.7332182e+09 | H52: =Inputs!B10*C52*Inputs!B14 -> 1.3081445e+12 | I52: =Inputs!B11*B52 -> 0 | J52: =IF(D52>0,H52/D52,0) -> 3025.692 | K52: =IF(D52>0,I52/D52/12,0) -> 0 | L52: =(L51+J52)*(1+Inputs!B17) -> 639877.06 | M52: =L52/E52 -> 639877.06 | N52: =N51+K52*12/E52 -> 0
A53: 48 | B53: =B52+G52+H52+I52 -> 63931890231477 | C53: =C52*(1+Inputs!B14)*(1+Inputs!B16) -> 7.9423061e+13 | D53: =D52*(1+Inputs!B15) -> 4.3450729e+08 | E53: =E52*(1+Inputs!B16) -> 1 | F53: =MAX(0,D53*Inputs!B15) -> 2172536.5 | G53: =Inputs!B9*(C53/D53)*F53 -> 9.9278826e+09 | H53: =Inputs!B10*C53*Inputs!B14 -> 1.3343074e+12 | I53: =Inputs!B11*B53 -> 0 | J53: =IF(D53>0,H53/D53,0) -> 3070.8516 | K53: =IF(D53>0,I53/D53/12,0) -> 0 | L53: =(L52+J53)*(1+Inputs!B17) -> 684739.53 | M53: =L53/E53 -> 684739.53 | N53: =N52+K53*12/E53 -> 0
A54: 49 | B54: =B53+G53+H53+I53 -> 6.5276126e+13 | C54: =C53*(1+Inputs!B14)*(1+Inputs!B16) -> 8.1011522e+13 | D54: =D53*(1+Inputs!B15) -> 4.3667983e+08 | E54: =E53*(1+Inputs!B16) -> 1 | F54: =MAX(0,D54*Inputs!B15) -> 2183399.1 | G54: =Inputs!B9*(C54/D54)*F54 -> 1.012644e+10 | H54: =Inputs!B10*C54*Inputs!B14 -> 1.3609936e+12 | I54: =Inputs!B11*B54 -> 0 | J54: =IF(D54>0,H54/D54,0) -> 3116.6852 | K54: =IF(D54>0,I54/D54/12,0) -> 0 | L54: =(L53+J54)*(1+Inputs!B17) -> 732566.87 | M54: =L54/E54 -> 732566.87 | N54: =N53+K54*12/E54 -> 0
A55: 50 | B55: =B54+G54+H54+I54 -> 6.6647246e+13 | C55: =C54*(1+Inputs!B14)*(1+Inputs!B16) -> 8.2631752e+13 | D55: =D54*(1+Inputs!B15) -> 4.3886323e+08 | E55: =E54*(1+Inputs!B16) -> 1 | F55: =MAX(0,D55*Inputs!B15) -> 2194316.1 | G55: =Inputs!B9*(C55/D55)*F55 -> 1.0328969e+10 | H55: =Inputs!B10*C55*Inputs!B14 -> 1388213441875 | I55: =Inputs!B11*B55 -> 0 | J55: =IF(D55>0,H55/D55,0) -> 3163.2029 | K55: =IF(D55>0,I55/D55/12,0) -> 0 | L55: =(L54+J55)*(1+Inputs!B17) -> 783552.53 | M55: =L55/E55 -> 783552.53 | N55: =N54+K55*12/E55 -> 0
A56: 51 | B56: =B55+G55+H55+I55 -> 6.8045788e+13 | C56: =C55*(1+Inputs!B14)*(1+Inputs!B16) -> 84284387542411 | D56: =D55*(1+Inputs!B15) -> 4.4105754e+08 | E56: =E55*(1+Inputs!B16) -> 1 | F56: =MAX(0,D56*Inputs!B15) -> 2205287.7 | G56: =Inputs!B9*(C56/D56)*F56 -> 1.0535548e+10 | H56: =Inputs!B10*C56*Inputs!B14 -> 1.4159777e+12 | I56: =Inputs!B11*B56 -> 0 | J56: =IF(D56>0,H56/D56,0) -> 3210.4149 | K56: =IF(D56>0,I56/D56/12,0) -> 0 | L56: =(L55+J56)*(1+Inputs!B17) -> 837902.53 | M56: =L56/E56 -> 837902.53 | N56: =N55+K56*12/E56 -> 0
A57: 52 | B57: =B56+G56+H56+I56 -> 6.9472301e+13 | C57: =C56*(1+Inputs!B14)*(1+Inputs!B16) -> 8.5970075e+13 | D57: =D56*(1+Inputs!B15) -> 4.4326283e+08 | E57: =E56*(1+Inputs!B16) -> 1 | F57: =MAX(0,D57*Inputs!B15) -> 2216314.2 | G57: =Inputs!B9*(C57/D57)*F57 -> 1.0746259e+10 | H57: =Inputs!B10*C57*Inputs!B14 -> 1.4442973e+12 | I57: =Inputs!B11*B57 -> 0 | J57: =IF(D57>0,H57/D57,0) -> 3258.3315 | K57: =IF(D57>0,I57/D57/12,0) -> 0 | L57: =(L56+J57)*(1+Inputs!B17) -> 895836.32 | M57: =L57/E57 -> 895836.32 | N57: =N56+K57*12/E57 -> 0
A58: 53 | B58: =B57+G57+H57+I57 -> 70927344741259 | C58: =C57*(1+Inputs!B14)*(1+Inputs!B16) -> 8.7689477e+13 | D58: =D57*(1+Inputs!B15) -> 4.4547915e+08 | E58: =E57*(1+Inputs!B16) -> 1 | F58: =MAX(0,D58*Inputs!B15) -> 2227395.7 | G58: =Inputs!B9*(C58/D58)*F58 -> 1.0961185e+10 | H58: =Inputs!B10*C58*Inputs!B14 -> 1.4731832e+12 | I58: =Inputs!B11*B58 -> 0 | J58: =IF(D58>0,H58/D58,0) -> 3306.9633 | K58: =IF(D58>0,I58/D58/12,0) -> 0 | L58: =(L57+J58)*(1+Inputs!B17) -> 957587.6 | M58: =L58/E58 -> 957587.6 | N58: =N57+K58*12/E58 -> 0
A59: 54 | B59: =B58+G58+H58+I58 -> 7.2411489e+13 | C59: =C58*(1+Inputs!B14)*(1+Inputs!B16) -> 8.9443266e+13 | D59: =D58*(1+Inputs!B15) -> 4.4770654e+08 | E59: =E58*(1+Inputs!B16) -> 1 | F59: =MAX(0,D59*Inputs!B15) -> 2238532.7 | G59: =Inputs!B9*(C59/D59)*F59 -> 1.1180408e+10 | H59: =Inputs!B10*C59*Inputs!B14 -> 1.5026469e+12 | I59: =Inputs!B11*B59 -> 0 | J59: =IF(D59>0,H59/D59,0) -> 3356.321 | K59: =IF(D59>0,I59/D59/12,0) -> 0 | L59: =(L58+J59)*(1+Inputs!B17) -> 1023405.3 | M59: =L59/E59 -> 1023405.3 | N59: =N58+K59*12/E59 -> 0
A60: 55 | B60: =B59+G59+H59+I59 -> 7.3925316e+13 | C60: =C59*(1+Inputs!B14)*(1+Inputs!B16) -> 91232131661809 | D60: =D59*(1+Inputs!B15) -> 4.4994508e+08 | E60: =E59*(1+Inputs!B16) -> 1 | F60: =MAX(0,D60*Inputs!B15) -> 2249725.4 | G60: =Inputs!B9*(C60/D60)*F60 -> 1.1404016e+10 | H60: =Inputs!B10*C60*Inputs!B14 -> 1.5326998e+12 | I60: =Inputs!B11*B60 -> 0 | J60: =IF(D60>0,H60/D60,0) -> 3406.4154 | K60: =IF(D60>0,I60/D60/12,0) -> 0 | L60: =(L59+J60)*(1+Inputs!B17) -> 1093554.4 | M60: =L60/E60 -> 1093554.4 | N60: =N59+K60*12/E60 -> 0
A61: 56 | B61: =B60+G60+H60+I60 -> 75469420247182 | C61: =C60*(1+Inputs!B14)*(1+Inputs!B16) -> 9.3056774e+13 | D61: =D60*(1+Inputs!B15) -> 4.521948e+08 | E61: =E60*(1+Inputs!B16) -> 1 | F61: =MAX(0,D61*Inputs!B15) -> 2260974 | G61: =Inputs!B9*(C61/D61)*F61 -> 1.1632097e+10 | H61: =Inputs!B10*C61*Inputs!B14 -> 1.5633538e+12 | I61: =Inputs!B11*B61 -> 0 | J61: =IF(D61>0,H61/D61,0) -> 3457.2574 | K61: =IF(D61>0,I61/D61/12,0) -> 0 | L61: =(L60+J61)*(1+Inputs!B17) -> 1168317.5 | M61: =L61/E61 -> 1168317.5 | N61: =N60+K61*12/E61 -> 0
A62: 57 | B62: =B61+G61+H61+I61 -> 7.7044406e+13 | C62: =C61*(1+Inputs!B14)*(1+Inputs!B16) -> 9.491791e+13 | D62: =D61*(1+Inputs!B15) -> 4.5445577e+08 | E62: =E61*(1+Inputs!B16) -> 1 | F62: =MAX(0,D62*Inputs!B15) -> 2272278.9 | G62: =Inputs!B9*(C62/D62)*F62 -> 1.1864739e+10 | H62: =Inputs!B10*C62*Inputs!B14 -> 1.5946209e+12 | I62: =Inputs!B11*B62 -> 0 | J62: =IF(D62>0,H62/D62,0) -> 3508.8582 | K62: =IF(D62>0,I62/D62/12,0) -> 0 | L62: =(L61+J62)*(1+Inputs!B17) -> 1247995 | M62: =L62/E62 -> 1247995 | N62: =N61+K62*12/E62 -> 0
A63: 58 | B63: =B62+G62+H62+I62 -> 7.8650892e+13 | C63: =C62*(1+Inputs!B14)*(1+Inputs!B16) -> 96816267976565 | D63: =D62*(1+Inputs!B15) -> 4.5672805e+08 | E63: =E62*(1+Inputs!B16) -> 1 | F63: =MAX(0,D63*Inputs!B15) -> 2283640.3 | G63: =Inputs!B9*(C63/D63)*F63 -> 1.2102033e+10 | H63: =Inputs!B10*C63*Inputs!B14 -> 1.6265133e+12 | I63: =Inputs!B11*B63 -> 0 | J63: =IF(D63>0,H63/D63,0) -> 3561.2292 | K63: =IF(D63>0,I63/D63/12,0) -> 0 | L63: =(L62+J63)*(1+Inputs!B17) -> 1332907.4 | M63: =L63/E63 -> 1332907.4 | N63: =N62+K63*12/E63 -> 0
A64: 59 | B64: =B63+G63+H63+I63 -> 8.0289507e+13 | C64: =C63*(1+Inputs!B14)*(1+Inputs!B16) -> 9.8752593e+13 | D64: =D63*(1+Inputs!B15) -> 4.5901169e+08 | E64: =E63*(1+Inputs!B16) -> 1 | F64: =MAX(0,D64*Inputs!B15) -> 2295058.5 | G64: =Inputs!B9*(C64/D64)*F64 -> 1.2344074e+10 | H64: =Inputs!B10*C64*Inputs!B14 -> 1.6590436e+12 | I64: =Inputs!B11*B64 -> 0 | J64: =IF(D64>0,H64/D64,0) -> 3614.3819 | K64: =IF(D64>0,I64/D64/12,0) -> 0 | L64: =(L63+J64)*(1+Inputs!B17) -> 1423395.7 | M64: =L64/E64 -> 1423395.7 | N64: =N63+K64*12/E64 -> 0
A65: 60 | B65: =B64+G64+H64+I64 -> 81960894752885 | C65: =C64*(1+Inputs!B14)*(1+Inputs!B16) -> 100727645202818 | D65: =D64*(1+Inputs!B15) -> 4.6130675e+08 | E65: =E64*(1+Inputs!B16) -> 1 | F65: =MAX(0,D65*Inputs!B15) -> 2306533.8 | G65: =Inputs!B9*(C65/D65)*F65 -> 1.2590956e+10 | H65: =Inputs!B10*C65*Inputs!B14 -> 1.6922244e+12 | I65: =Inputs!B11*B65 -> 0 | J65: =IF(D65>0,H65/D65,0) -> 3668.3279 | K65: =IF(D65>0,I65/D65/12,0) -> 0 | L65: =(L64+J65)*(1+Inputs!B17) -> 1519823.2 | M65: =L65/E65 -> 1519823.2 | N65: =N64+K65*12/E65 -> 0
A66: 61 | B66: =B65+G65+H65+I65 -> 8.366571e+13 | C66: =C65*(1+Inputs!B14)*(1+Inputs!B16) -> 102742198106875 | D66: =D65*(1+Inputs!B15) -> 4.6361329e+08 | E66: =E65*(1+Inputs!B16) -> 1 | F66: =MAX(0,D66*Inputs!B15) -> 2318066.4 | G66: =Inputs!B9*(C66/D66)*F66 -> 1.2842775e+10 | H66: =Inputs!B10*C66*Inputs!B14 -> 1.7260689e+12 | I66: =Inputs!B11*B66 -> 0 | J66: =IF(D66>0,H66/D66,0) -> 3723.0791 | K66: =IF(D66>0,I66/D66/12,0) -> 0 | L66: =(L65+J66)*(1+Inputs!B17) -> 1622576.8 | M66: =L66/E66 -> 1622576.8 | N66: =N65+K66*12/E66 -> 0
A67: 62 | B67: =B66+G66+H66+I66 -> 8.5404622e+13 | C67: =C66*(1+Inputs!B14)*(1+Inputs!B16) -> 104797042069012 | D67: =D66*(1+Inputs!B15) -> 4.6593135e+08 | E67: =E66*(1+Inputs!B16) -> 1 | F67: =MAX(0,D67*Inputs!B15) -> 2329656.8 | G67: =Inputs!B9*(C67/D67)*F67 -> 1.309963e+10 | H67: =Inputs!B10*C67*Inputs!B14 -> 1.7605903e+12 | I67: =Inputs!B11*B67 -> 0 | J67: =IF(D67>0,H67/D67,0) -> 3778.6474 | K67: =IF(D67>0,I67/D67/12,0) -> 0 | L67: =(L66+J67)*(1+Inputs!B17) -> 1732068.6 | M67: =L67/E67 -> 1732068.6 | N67: =N66+K67*12/E67 -> 0
A68: 63 | B68: =B67+G67+H67+I67 -> 8.7178312e+13 | C68: =C67*(1+Inputs!B14)*(1+Inputs!B16) -> 106892982910392 | D68: =D67*(1+Inputs!B15) -> 4.6826101e+08 | E68: =E67*(1+Inputs!B16) -> 1 | F68: =MAX(0,D68*Inputs!B15) -> 2341305 | G68: =Inputs!B9*(C68/D68)*F68 -> 1.3361623e+10 | H68: =Inputs!B10*C68*Inputs!B14 -> 1.7958021e+12 | I68: =Inputs!B11*B68 -> 0 | J68: =IF(D68>0,H68/D68,0) -> 3835.0452 | K68: =IF(D68>0,I68/D68/12,0) -> 0 | L68: =(L67+J68)*(1+Inputs!B17) -> 1848737.3 | M68: =L68/E68 -> 1848737.3 | N68: =N67+K68*12/E68 -> 0
A69: 64 | B69: =B68+G68+H68+I68 -> 8.8987476e+13 | C69: =C68*(1+Inputs!B14)*(1+Inputs!B16) -> 109030842568600 | D69: =D68*(1+Inputs!B15) -> 4.7060231e+08 | E69: =E68*(1+Inputs!B16) -> 1 | F69: =MAX(0,D69*Inputs!B15) -> 2353011.6 | G69: =Inputs!B9*(C69/D69)*F69 -> 1.3628855e+10 | H69: =Inputs!B10*C69*Inputs!B14 -> 1.8317182e+12 | I69: =Inputs!B11*B69 -> 0 | J69: =IF(D69>0,H69/D69,0) -> 3892.2846 | K69: =IF(D69>0,I69/D69/12,0) -> 0 | L69: =(L68+J69)*(1+Inputs!B17) -> 1973050.5 | M69: =L69/E69 -> 1973050.5 | N69: =N68+K69*12/E69 -> 0
A70: 65 | B70: =B69+G69+H69+I69 -> 9.0832823e+13 | C70: =C69*(1+Inputs!B14)*(1+Inputs!B16) -> 111211459419972 | D70: =D69*(1+Inputs!B15) -> 4.7295533e+08 | E70: =E69*(1+Inputs!B16) -> 1 | F70: =MAX(0,D70*Inputs!B15) -> 2364776.6 | G70: =Inputs!B9*(C70/D70)*F70 -> 1.3901432e+10 | H70: =Inputs!B10*C70*Inputs!B14 -> 1.8683525e+12 | I70: =Inputs!B11*B70 -> 0 | J70: =IF(D70>0,H70/D70,0) -> 3950.3784 | K70: =IF(D70>0,I70/D70/12,0) -> 0 | L70: =(L69+J70)*(1+Inputs!B17) -> 2105506 | M70: =L70/E70 -> 2105506 | N70: =N69+K70*12/E70 -> 0
A71: 66 | B71: =B70+G70+H70+I70 -> 9.2715076e+13 | C71: =C70*(1+Inputs!B14)*(1+Inputs!B16) -> 113435688608372 | D71: =D70*(1+Inputs!B15) -> 4.753201e+08 | E71: =E70*(1+Inputs!B16) -> 1 | F71: =MAX(0,D71*Inputs!B15) -> 2376600.5 | G71: =Inputs!B9*(C71/D71)*F71 -> 1.4179461e+10 | H71: =Inputs!B10*C71*Inputs!B14 -> 1.9057196e+12 | I71: =Inputs!B11*B71 -> 0 | J71: =IF(D71>0,H71/D71,0) -> 4009.3393 | K71: =IF(D71>0,I71/D71/12,0) -> 0 | L71: =(L70+J71)*(1+Inputs!B17) -> 2246633.8 | M71: =L71/E71 -> 2246633.8 | N71: =N70+K71*12/E71 -> 0
A72: 67 | B72: =B71+G71+H71+I71 -> 9.4634976e+13 | C72: =C71*(1+Inputs!B14)*(1+Inputs!B16) -> 115704402380539 | D72: =D71*(1+Inputs!B15) -> 4.776967e+08 | E72: =E71*(1+Inputs!B16) -> 1 | F72: =MAX(0,D72*Inputs!B15) -> 2388483.5 | G72: =Inputs!B9*(C72/D72)*F72 -> 1.446305e+10 | H72: =Inputs!B10*C72*Inputs!B14 -> 1.943834e+12 | I72: =Inputs!B11*B72 -> 0 | J72: =IF(D72>0,H72/D72,0) -> 4069.1802 | K72: =IF(D72>0,I72/D72/12,0) -> 0 | L72: =(L71+J72)*(1+Inputs!B17) -> 2396998.7 | M72: =L72/E72 -> 2396998.7 | N72: =N71+K72*12/E72 -> 0
A73: 68 | B73: =B72+G72+H72+I72 -> 9.6593273e+13 | C73: =C72*(1+Inputs!B14)*(1+Inputs!B16) -> 118018490428150 | D73: =D72*(1+Inputs!B15) -> 4.8008519e+08 | E73: =E72*(1+Inputs!B16) -> 1 | F73: =MAX(0,D73*Inputs!B15) -> 2400425.9 | G73: =Inputs!B9*(C73/D73)*F73 -> 1.4752311e+10 | H73: =Inputs!B10*C73*Inputs!B14 -> 1.9827106e+12 | I73: =Inputs!B11*B73 -> 0 | J73: =IF(D73>0,H73/D73,0) -> 4129.9142 | K73: =IF(D73>0,I73/D73/12,0) -> 0 | L73: =(L72+J73)*(1+Inputs!B17) -> 2557202 | M73: =L73/E73 -> 2557202 | N73: =N72+K73*12/E73 -> 0
A74: 69 | B74: =B73+G73+H73+I73 -> 9.8590735e+13 | C74: =C73*(1+Inputs!B14)*(1+Inputs!B16) -> 120378860236713 | D74: =D73*(1+Inputs!B15) -> 4.8248561e+08 | E74: =E73*(1+Inputs!B16) -> 1 | F74: =MAX(0,D74*Inputs!B15) -> 2412428.1 | G74: =Inputs!B9*(C74/D74)*F74 -> 1.5047358e+10 | H74: =Inputs!B10*C74*Inputs!B14 -> 2.0223649e+12 | I74: =Inputs!B11*B74 -> 0 | J74: =IF(D74>0,H74/D74,0) -> 4191.5547 | K74: =IF(D74>0,I74/D74/12,0) -> 0 | L74: =(L73+J74)*(1+Inputs!B17) -> 2727884.1 | M74: =L74/E74 -> 2727884.1 | N74: =N73+K74*12/E74 -> 0
A75: 70 | B75: =B74+G74+H74+I74 -> 100628147684825 | C75: =C74*(1+Inputs!B14)*(1+Inputs!B16) -> 122786437441447 | D75: =D74*(1+Inputs!B15) -> 4.8489804e+08 | E75: =E74*(1+Inputs!B16) -> 1 | F75: =MAX(0,D75*Inputs!B15) -> 2424490.2 | G75: =Inputs!B9*(C75/D75)*F75 -> 1.5348305e+10 | H75: =Inputs!B10*C75*Inputs!B14 -> 2.0628121e+12 | I75: =Inputs!B11*B75 -> 0 | J75: =IF(D75>0,H75/D75,0) -> 4254.1153 | K75: =IF(D75>0,I75/D75/12,0) -> 0 | L75: =(L74+J75)*(1+Inputs!B17) -> 2909727.2 | M75: =L75/E75 -> 2909727.2 | N75: =N74+K75*12/E75 -> 0
A76: 71 | B76: =B75+G75+H75+I75 -> 102706308138521 | C76: =C75*(1+Inputs!B14)*(1+Inputs!B16) -> 125242166190276 | D76: =D75*(1+Inputs!B15) -> 4.8732253e+08 | E76: =E75*(1+Inputs!B16) -> 1 | F76: =MAX(0,D76*Inputs!B15) -> 2436612.7 | G76: =Inputs!B9*(C76/D76)*F76 -> 1.5655271e+10 | H76: =Inputs!B10*C76*Inputs!B14 -> 2.1040684e+12 | I76: =Inputs!B11*B76 -> 0 | J76: =IF(D76>0,H76/D76,0) -> 4317.6095 | K76: =IF(D76>0,I76/D76/12,0) -> 0 | L76: =(L75+J76)*(1+Inputs!B17) -> 3103457.7 | M76: =L76/E76 -> 3103457.7 | N76: =N75+K76*12/E76 -> 0
A77: 72 | B77: =B76+G76+H76+I76 -> 104826031801292 | C77: =C76*(1+Inputs!B14)*(1+Inputs!B16) -> 127747009514082 | D77: =D76*(1+Inputs!B15) -> 4.8975914e+08 | E77: =E76*(1+Inputs!B16) -> 1 | F77: =MAX(0,D77*Inputs!B15) -> 2448795.7 | G77: =Inputs!B9*(C77/D77)*F77 -> 1.5968376e+10 | H77: =Inputs!B10*C77*Inputs!B14 -> 2.1461498e+12 | I77: =Inputs!B11*B77 -> 0 | J77: =IF(D77>0,H77/D77,0) -> 4382.0514 | K77: =IF(D77>0,I77/D77/12,0) -> 0 | L77: =(L76+J77)*(1+Inputs!B17) -> 3309849.4 | M77: =L77/E77 -> 3309849.4 | N77: =N76+K77*12/E77 -> 0
A78: 73 | B78: =B77+G77+H77+I77 -> 106988149937317 | C78: =C77*(1+Inputs!B14)*(1+Inputs!B16) -> 130301949704363 | D78: =D77*(1+Inputs!B15) -> 4.9220794e+08 | E78: =E77*(1+Inputs!B16) -> 1 | F78: =MAX(0,D78*Inputs!B15) -> 2461039.7 | G78: =Inputs!B9*(C78/D78)*F78 -> 1.6287744e+10 | H78: =Inputs!B10*C78*Inputs!B14 -> 2.1890728e+12 | I78: =Inputs!B11*B78 -> 0 | J78: =IF(D78>0,H78/D78,0) -> 4447.4552 | K78: =IF(D78>0,I78/D78/12,0) -> 0 | L78: =(L77+J78)*(1+Inputs!B17) -> 3529726.1 | M78: =L78/E78 -> 3529726.1 | N78: =N77+K78*12/E78 -> 0
A79: 74 | B79: =B78+G78+H78+I78 -> 109193510436064 | C79: =C78*(1+Inputs!B14)*(1+Inputs!B16) -> 132907988698451 | D79: =D78*(1+Inputs!B15) -> 4.9466898e+08 | E79: =E78*(1+Inputs!B16) -> 1 | F79: =MAX(0,D79*Inputs!B15) -> 2473344.9 | G79: =Inputs!B9*(C79/D79)*F79 -> 1.6613499e+10 | H79: =Inputs!B10*C79*Inputs!B14 -> 2.2328542e+12 | I79: =Inputs!B11*B79 -> 0 | J79: =IF(D79>0,H79/D79,0) -> 4513.8351 | K79: =IF(D79>0,I79/D79/12,0) -> 0 | L79: =(L78+J79)*(1+Inputs!B17) -> 3763965.5 | M79: =L79/E79 -> 3763965.5 | N79: =N78+K79*12/E79 -> 0
A80: 75 | B80: =B79+G79+H79+I79 -> 111442978144785 | C80: =C79*(1+Inputs!B14)*(1+Inputs!B16) -> 135566148472420 | D80: =D79*(1+Inputs!B15) -> 4.9714232e+08 | E80: =E79*(1+Inputs!B16) -> 1 | F80: =MAX(0,D80*Inputs!B15) -> 2485711.6 | G80: =Inputs!B9*(C80/D80)*F80 -> 1.6945769e+10 | H80: =Inputs!B10*C80*Inputs!B14 -> 2.2775113e+12 | I80: =Inputs!B11*B80 -> 0 | J80: =IF(D80>0,H80/D80,0) -> 4581.2058 | K80: =IF(D80>0,I80/D80/12,0) -> 0 | L80: =(L79+J80)*(1+Inputs!B17) -> 4013502.3 | M80: =L80/E80 -> 4013502.3 | N80: =N79+K80*12/E80 -> 0
A81: 76 | B81: =B80+G80+H80+I80 -> 113737435207681 | C81: =C80*(1+Inputs!B14)*(1+Inputs!B16) -> 138277471441868 | D81: =D80*(1+Inputs!B15) -> 4.9962804e+08 | E81: =E80*(1+Inputs!B16) -> 1 | F81: =MAX(0,D81*Inputs!B15) -> 2498140.2 | G81: =Inputs!B9*(C81/D81)*F81 -> 1.7284684e+10 | H81: =Inputs!B10*C81*Inputs!B14 -> 2.3230615e+12 | I81: =Inputs!B11*B81 -> 0 | J81: =IF(D81>0,H81/D81,0) -> 4649.582 | K81: =IF(D81>0,I81/D81/12,0) -> 0 | L81: =(L80+J81)*(1+Inputs!B17) -> 4279331.7 | M81: =L81/E81 -> 4279331.7 | N81: =N80+K81*12/E81 -> 0
A82: 77 | B82: =B81+G81+H81+I81 -> 116077781411834 | C82: =C81*(1+Inputs!B14)*(1+Inputs!B16) -> 141043020870705 | D82: =D81*(1+Inputs!B15) -> 5.0212618e+08 | E82: =E81*(1+Inputs!B16) -> 1 | F82: =MAX(0,D82*Inputs!B15) -> 2510630.9 | G82: =Inputs!B9*(C82/D82)*F82 -> 1.7630378e+10 | H82: =Inputs!B10*C82*Inputs!B14 -> 2.3695228e+12 | I82: =Inputs!B11*B82 -> 0 | J82: =IF(D82>0,H82/D82,0) -> 4718.9787 | K82: =IF(D82>0,I82/D82/12,0) -> 0 | L82: =(L81+J82)*(1+Inputs!B17) -> 4562514 | M82: =L82/E82 -> 4562514 | N82: =N81+K82*12/E82 -> 0
A83: 78 | B83: =B82+G82+H82+I82 -> 118464934540071 | C83: =C82*(1+Inputs!B14)*(1+Inputs!B16) -> 143863881288119 | D83: =D82*(1+Inputs!B15) -> 5.0463681e+08 | E83: =E82*(1+Inputs!B16) -> 1 | F83: =MAX(0,D83*Inputs!B15) -> 2523184 | G83: =Inputs!B9*(C83/D83)*F83 -> 1.7982985e+10 | H83: =Inputs!B10*C83*Inputs!B14 -> 2.4169132e+12 | I83: =Inputs!B11*B83 -> 0 | J83: =IF(D83>0,H83/D83,0) -> 4789.4113 | K83: =IF(D83>0,I83/D83/12,0) -> 0 | L83: =(L82+J83)*(1+Inputs!B17) -> 4864178.1 | M83: =L83/E83 -> 4864178.1 | N83: =N82+K83*12/E83 -> 0
A84: 79 | B84: =B83+G83+H83+I83 -> 120899830730872 | C84: =C83*(1+Inputs!B14)*(1+Inputs!B16) -> 146741158913882 | D84: =D83*(1+Inputs!B15) -> 5.0715999e+08 | E84: =E83*(1+Inputs!B16) -> 1 | F84: =MAX(0,D84*Inputs!B15) -> 2535800 | G84: =Inputs!B9*(C84/D84)*F84 -> 1.8342645e+10 | H84: =Inputs!B10*C84*Inputs!B14 -> 2.4652515e+12 | I84: =Inputs!B11*B84 -> 0 | J84: =IF(D84>0,H84/D84,0) -> 4860.895 | K84: =IF(D84>0,I84/D84/12,0) -> 0 | L84: =(L83+J84)*(1+Inputs!B17) -> 5185526.6 | M84: =L84/E84 -> 5185526.6 | N84: =N83+K84*12/E84 -> 0
A85: 80 | B85: =B84+G84+H84+I84 -> 123383424845490 | C85: =C84*(1+Inputs!B14)*(1+Inputs!B16) -> 149675982092159 | D85: =D84*(1+Inputs!B15) -> 5.0969579e+08 | E85: =E84*(1+Inputs!B16) -> 1 | F85: =MAX(0,D85*Inputs!B15) -> 2548479 | G85: =Inputs!B9*(C85/D85)*F85 -> 1.8709498e+10 | H85: =Inputs!B10*C85*Inputs!B14 -> 2.5145565e+12 | I85: =Inputs!B11*B85 -> 0 | J85: =IF(D85>0,H85/D85,0) -> 4933.4457 | K85: =IF(D85>0,I85/D85/12,0) -> 0 | L85: =(L84+J85)*(1+Inputs!B17) -> 5527839.9 | M85: =L85/E85 -> 5527839.9 | N85: =N84+K85*12/E85 -> 0

Sheet Summary
A1: Headline outcomes at horizon
A2: Pulled live from Projection sheet using the Inputs!horizon value.
A4: Output | B4: Value | C4: Definition
A5: Stable Floor at horizon (real $) | B5: =INDEX(Projection!M5:M85,MATCH(Inputs!B23,Projection!A5:A85,0)) -> 2105506 | C5: Locked equity for one citizen, in launch-year purchasing power.
A6: Annual real income at horizon | B6: =INDEX(Projection!M5:M85,MATCH(Inputs!B23,Projection!A5:A85,0))*Inputs!B24 -> 84220.239 | C6: Stable Floor × withdrawal rate.
A7: K3 monthly dividend, year 1 | B7: =INDEX(Projection!K5:K85,2) -> 0 | C7: K3 spendable dividend per citizen, first year.
A8: K3 cumulative lifetime (real $) | B8: =INDEX(Projection!N5:N85,MATCH(Inputs!B23,Projection!A5:A85,0)) -> 0 | C8: Total dividend received by horizon, today dollars.
A9: Total real wealth at horizon | B9: =INDEX(Projection!M5:M85,MATCH(Inputs!B23,Projection!A5:A85,0))+INDEX(Projection!N5:N85,MATCH(Inputs!B23,Projection!A5:A85,0)) -> 2105506 | C9: Stable Floor + cumulative K3 (both real $).
A10: Total issuance / M2, year 1 | B10: =(INDEX(Projection!G5:G85,2)+INDEX(Projection!H5:H85,2)+INDEX(Projection!I5:I85,2))/INDEX(Projection!B5:B85,2) -> 0.022825092 | C10: Annual K1+K2+K3 as fraction of money supply.
A11: Total issuance / GDP, year 1 | B11: =(INDEX(Projection!G5:G85,2)+INDEX(Projection!H5:H85,2)+INDEX(Projection!I5:I85,2))/INDEX(Projection!C5:C85,2) -> 0.016925 | C11: Annual K1+K2+K3 as fraction of GDP.
A12: M2 at horizon ($) | B12: =INDEX(Projection!B5:B85,MATCH(Inputs!B23,Projection!A5:A85,0)) -> 9.0832823e+13 | C12: Final money supply.
A13: GDP at horizon ($) | B13: =INDEX(Projection!C5:C85,MATCH(Inputs!B23,Projection!A5:A85,0)) -> 111211459419972 | C13: Final nominal GDP.
A14: Population at horizon | B14: =INDEX(Projection!D5:D85,MATCH(Inputs!B23,Projection!A5:A85,0)) -> 4.7295533e+08 | C14: Final citizen count.
A15: CPI index at horizon | B15: =INDEX(Projection!E5:E85,MATCH(Inputs!B23,Projection!A5:A85,0)) -> 1 | C15: Price level relative to launch (1.0 = no change).

Sheet Comparison
A1: How does the Citizens Standard compare to real-world outcomes?
A2: Each column shows what one citizen actually receives under that system, using real-world median data — not theoretical maximums. Toggle the scenario in the yellow cell below to switch between median, average, and post-SS-cut outcomes.
A4: Real-world data anchors
A5: Median 401(k) at age 55-64 | B5: 87571 | C5: Vanguard 2025 — half of Americans have less
A6: Average 401(k) at age 55-64 | B6: 244750 | C6: Vanguard 2025 — skewed by top earners
A7: Average SS benefit (annual) | B7: 24953 | C7: SSA Mar 2026 — $2,079.49/mo × 12
A8: SS benefit cut after trust depletion | B8: 0.23 | C8: 2025 SSA Trustees Report — projected ~2034
A9: Alaska PFD (annual) | B9: 1700 | C9: Alaska DOR — recent average
A10: UBI proposal (monthly) | B10: 1000 | C10: Adjustable — common UBI proposal level
A11: MMT jobs guarantee wage | B11: 31200 | C11: $15/hr × 2080 hrs
A13: Scenario | B13: median | C13: Type: median, average, or ss-cut
A15: Lifetime delivery to one citizen, age 0 → horizon
A16: Metric | B16: Citizens Standard | C16: Fed status quo + SS | D16: Chicago Plan | E16: Friedman k-rule | F16: Bitcoin / fixed supply | G16: Alaska PFD (US-scale) | H16: UBI (tax-funded) | I16: MMT + jobs guarantee
A17: Wealth at horizon (real $) | B17: =Summary!B5 -> 2105506 | C17: =IF($B$13="average",$B$6,$B$5) -> 87571 | D17: =IF($B$13="average",$B$6,$B$5) -> 87571 | E17: =IF($B$13="average",$B$6,$B$5) -> 87571 | F17: =IF($B$13="average",$B$6,$B$5) -> 87571 | G17: =IF($B$13="average",$B$6,$B$5) -> 87571 | H17: =IF($B$13="average",$B$6,$B$5) -> 87571 | I17: =IF($B$13="average",$B$6,$B$5) -> 87571
A18: Lifetime cash transfers (real $) | B18: =Summary!B8 -> 0 | C18: 0 | D18: 0 | E18: 0 | F18: 0 | G18: =$B$9*Inputs!B23 -> 110500 | H18: =$B$10*12*Inputs!B23 -> 780000 | I18: =$B$11*43 -> 1341600
A19: Annual retirement income | B19: =Summary!B5*Inputs!B24+Projection!K5*12 -> 84220.239 | C19: =IF($B$13="average",$B$6,$B$5)*Inputs!B24+IF($B$13="ss-cut",$B$7*(1-$B$8),$B$7) -> 28455.84 | D19: =IF($B$13="average",$B$6,$B$5)*Inputs!B24 -> 3502.84 | E19: =IF($B$13="average",$B$6,$B$5)*Inputs!B24 -> 3502.84 | F19: =IF($B$13="average",$B$6,$B$5)*Inputs!B24 -> 3502.84 | G19: =IF($B$13="average",$B$6,$B$5)*Inputs!B24+$B$9 -> 5202.84 | H19: =IF($B$13="average",$B$6,$B$5)*Inputs!B24+$B$10*12 -> 15502.84 | I19: =IF($B$13="average",$B$6,$B$5)*Inputs!B24 -> 3502.84
A21: Structural properties
A22: Rules-based (no committee discretion) | B22: ✓ | C22: ✗ | D22: ✓ | E22: ✓ | F22: ✓ | G22: partial | H22: ✗ | I22: ✗
A23: Per-citizen distribution | B23: ✓ | C23: ✗ | D23: ✗ | E23: ✗ | F23: ✗ | G23: ✓ | H23: ✓ | I23: partial
A24: Real-growth response | B24: ✓ | C24: partial | D24: ✗ | E24: ✗ | F24: ✗ | G24: partial | H24: ✗ | I24: ✓
A25: Crisis response capacity | B25: bounded | C25: unbounded | D25: limited | E25: none | F25: none | G25: limited | H25: limited | I25: unbounded
A26: Constitutional / hard to revoke | B26: ✓ | C26: ✗ | D26: ✗ | E26: ✗ | F26: ✓ | G26: ✗ | H26: ✗ | I26: ✗
A27: Funded by | B27: Seigniorage | C27: Mixed | D27: Govt seigniorage | E27: Fed seigniorage | F27: Mining rewards | G27: Resource royalty | H27: Taxation | I27: Treasury seigniorage
A29: Honest caveats
A30: Citizens Standard | B30: Single-cohort projection with constant rates. K3 modeled as flat % of M2 (not full price-level path targeting). Real values use your CPI input.
A31: Fed status quo | B31: Uses real-world median 401(k) balance ($87,571 at 55-64, Vanguard 2025) — what Americans actually retire with, not what disciplined savers theoretically could. Add SS at scenario-appropriate level.
A32: Chicago Plan | B32: 1933 proposal eliminated bank money creation but never specified seigniorage distribution. Citizens still rely on personal savings.
A33: Friedman k-rule | B33: Specified rate of monetary expansion but never the distribution channel. Nothing reaches citizens directly.
A34: Bitcoin | B34: Treated as savings vehicle with same equity-equivalent return for fair comparison. Real Bitcoin returns have been wildly volatile.
A35: Alaska PFD | B35: Modeled at $1,700/yr default. Real Alaska PFD funded by oil royalties, not seigniorage.
A36: UBI | B36: Funded by taxation, not money creation. Fiscal sustainability question is real and unresolved at scale.
A37: MMT | B37: Assumes citizen employed in jobs guarantee for full 43-year working life. Inflation control depends on tax policy responding correctly to demand pressure.
A39: Data sources
A40: Vanguard, How America Saves 2025: median 401(k) at 55-64 = $87,571; average = $244,750.
A41: Social Security Administration, Monthly Statistical Snapshot, March 2026: average retired-worker benefit = $2,079.49/month.
A42: 2025 SSA Trustees Report: OASI trust fund projected to deplete ~2034; benefits cut to ~77-81% of scheduled.
A43: SSA/CBO replacement rate analyses: ~37-42% for average earner.
A44: Alaska Department of Revenue: PFD historical range $1,200-$3,300/year.

Sheet Stress Test
A1: Stress Test — Historical Adverse Sequences
A2: What happens to the Stable Floor when a citizen lives through a real historical bad period? Each scenario applies year-by-year actual returns and inflation from a real era. The framework's structural advantage is what survives this stress test.
A4: Year-by-year simulation
A5: Year | B5: Age | C5: Smooth baseline | G5: Great Depression (1929-1944) | K5: 1970s Stagflation (1966-1982) | O5: 2000s Lost Decade (2000-2009)
C6: Return | D6: CPI | E6: Floor (nom) | F6: Floor (real) | G6: Return | H6: CPI | I6: Floor (nom) | J6: Floor (real) | K6: Return | L6: CPI | M6: Floor (nom) | N6: Floor (real) | O6: Return | P6: CPI | Q6: Floor (nom) | R6: Floor (real)
A7: 0 | B7: 0 | C7: =Inputs!B17 -> 0.065 | D7: =Inputs!B16 -> 0 | E7: =((Projection!G5/MAX(Projection!F5,1))+Projection!J5)*(1+C7) -> 3996.1167 | F7: =E7/(1+Inputs!B16)^(0+1) -> 3996.1167 | G7: =Inputs!B17 -> 0.065 | H7: =Inputs!B16 -> 0 | I7: =((Projection!G5/MAX(Projection!F5,1))+Projection!J5)*(1+G7) -> 3996.1167 | J7: =I7/(1+H7) -> 3996.1167 | K7: =Inputs!B17 -> 0.065 | L7: =Inputs!B16 -> 0 | M7: =((Projection!G5/MAX(Projection!F5,1))+Projection!J5)*(1+K7) -> 3996.1167 | N7: =M7/(1+L7) -> 3996.1167 | O7: =Inputs!B17 -> 0.065 | P7: =Inputs!B16 -> 0 | Q7: =((Projection!G5/MAX(Projection!F5,1))+Projection!J5)*(1+O7) -> 3996.1167 | R7: =Q7/(1+P7) -> 3996.1167
A8: 1 | B8: 1 | C8: =Inputs!B17 -> 0.065 | D8: =Inputs!B16 -> 0 | E8: =(E7+Projection!J6)*(1+C8) -> 5885.9306 | F8: =E8/(1+Inputs!B16)^(1+1) -> 5885.9306 | G8: =Inputs!B17 -> 0.065 | H8: =Inputs!B16 -> 0 | I8: =(I7+Projection!J6)*(1+G8) -> 5885.9306 | J8: =I8/PRODUCT(1+H$7:H8) -> 5885.9306 | K8: =Inputs!B17 -> 0.065 | L8: =Inputs!B16 -> 0 | M8: =(M7+Projection!J6)*(1+K8) -> 5885.9306 | N8: =M8/PRODUCT(1+L$7:L8) -> 5885.9306 | O8: =Inputs!B17 -> 0.065 | P8: =Inputs!B16 -> 0 | Q8: =(Q7+Projection!J6)*(1+O8) -> 5885.9306 | R8: =Q8/PRODUCT(1+P$7:P8) -> 5885.9306
A9: 2 | B9: 2 | C9: =Inputs!B17 -> 0.065 | D9: =Inputs!B16 -> 0 | E9: =(E8+Projection!J7)*(1+C9) -> 7922.9117 | F9: =E9/(1+Inputs!B16)^(2+1) -> 7922.9117 | G9: =Inputs!B17 -> 0.065 | H9: =Inputs!B16 -> 0 | I9: =(I8+Projection!J7)*(1+G9) -> 7922.9117 | J9: =I9/PRODUCT(1+H$7:H9) -> 7922.9117 | K9: =Inputs!B17 -> 0.065 | L9: =Inputs!B16 -> 0 | M9: =(M8+Projection!J7)*(1+K9) -> 7922.9117 | N9: =M9/PRODUCT(1+L$7:L9) -> 7922.9117 | O9: =Inputs!B17 -> 0.065 | P9: =Inputs!B16 -> 0 | Q9: =(Q8+Projection!J7)*(1+O9) -> 7922.9117 | R9: =Q9/PRODUCT(1+P$7:P9) -> 7922.9117
A10: 3 | B10: 3 | C10: =Inputs!B17 -> 0.065 | D10: =Inputs!B16 -> 0 | E10: =(E9+Projection!J8)*(1+C10) -> 10116.989 | F10: =E10/(1+Inputs!B16)^(3+1) -> 10116.989 | G10: =Inputs!B17 -> 0.065 | H10: =Inputs!B16 -> 0 | I10: =(I9+Projection!J8)*(1+G10) -> 10116.989 | J10: =I10/PRODUCT(1+H$7:H10) -> 10116.989 | K10: =Inputs!B17 -> 0.065 | L10: =Inputs!B16 -> 0 | M10: =(M9+Projection!J8)*(1+K10) -> 10116.989 | N10: =M10/PRODUCT(1+L$7:L10) -> 10116.989 | O10: =Inputs!B17 -> 0.065 | P10: =Inputs!B16 -> 0 | Q10: =(Q9+Projection!J8)*(1+O10) -> 10116.989 | R10: =Q10/PRODUCT(1+P$7:P10) -> 10116.989
A11: 4 | B11: 4 | C11: =Inputs!B17 -> 0.065 | D11: =Inputs!B16 -> 0 | E11: =(E10+Projection!J9)*(1+C11) -> 12478.742 | F11: =E11/(1+Inputs!B16)^(4+1) -> 12478.742 | G11: =Inputs!B17 -> 0.065 | H11: =Inputs!B16 -> 0 | I11: =(I10+Projection!J9)*(1+G11) -> 12478.742 | J11: =I11/PRODUCT(1+H$7:H11) -> 12478.742 | K11: =Inputs!B17 -> 0.065 | L11: =Inputs!B16 -> 0 | M11: =(M10+Projection!J9)*(1+K11) -> 12478.742 | N11: =M11/PRODUCT(1+L$7:L11) -> 12478.742 | O11: =Inputs!B17 -> 0.065 | P11: =Inputs!B16 -> 0 | Q11: =(Q10+Projection!J9)*(1+O11) -> 12478.742 | R11: =Q11/PRODUCT(1+P$7:P11) -> 12478.742
A12: 5 | B12: 5 | C12: =Inputs!B17 -> 0.065 | D12: =Inputs!B16 -> 0 | E12: =(E11+Projection!J10)*(1+C12) -> 15019.445 | F12: =E12/(1+Inputs!B16)^(5+1) -> 15019.445 | G12: =Inputs!B17 -> 0.065 | H12: =Inputs!B16 -> 0 | I12: =(I11+Projection!J10)*(1+G12) -> 15019.445 | J12: =I12/PRODUCT(1+H$7:H12) -> 15019.445 | K12: =Inputs!B17 -> 0.065 | L12: =Inputs!B16 -> 0 | M12: =(M11+Projection!J10)*(1+K12) -> 15019.445 | N12: =M12/PRODUCT(1+L$7:L12) -> 15019.445 | O12: =Inputs!B17 -> 0.065 | P12: =Inputs!B16 -> 0 | Q12: =(Q11+Projection!J10)*(1+O12) -> 15019.445 | R12: =Q12/PRODUCT(1+P$7:P12) -> 15019.445
A13: 6 | B13: 6 | C13: =Inputs!B17 -> 0.065 | D13: =Inputs!B16 -> 0 | E13: =(E12+Projection!J11)*(1+C13) -> 17751.108 | F13: =E13/(1+Inputs!B16)^(6+1) -> 17751.108 | G13: =Inputs!B17 -> 0.065 | H13: =Inputs!B16 -> 0 | I13: =(I12+Projection!J11)*(1+G13) -> 17751.108 | J13: =I13/PRODUCT(1+H$7:H13) -> 17751.108 | K13: =Inputs!B17 -> 0.065 | L13: =Inputs!B16 -> 0 | M13: =(M12+Projection!J11)*(1+K13) -> 17751.108 | N13: =M13/PRODUCT(1+L$7:L13) -> 17751.108 | O13: =Inputs!B17 -> 0.065 | P13: =Inputs!B16 -> 0 | Q13: =(Q12+Projection!J11)*(1+O13) -> 17751.108 | R13: =Q13/PRODUCT(1+P$7:P13) -> 17751.108
A14: 7 | B14: 7 | C14: =Inputs!B17 -> 0.065 | D14: =Inputs!B16 -> 0 | E14: =(E13+Projection!J12)*(1+C14) -> 20686.529 | F14: =E14/(1+Inputs!B16)^(7+1) -> 20686.529 | G14: =Inputs!B17 -> 0.065 | H14: =Inputs!B16 -> 0 | I14: =(I13+Projection!J12)*(1+G14) -> 20686.529 | J14: =I14/PRODUCT(1+H$7:H14) -> 20686.529 | K14: =Inputs!B17 -> 0.065 | L14: =Inputs!B16 -> 0 | M14: =(M13+Projection!J12)*(1+K14) -> 20686.529 | N14: =M14/PRODUCT(1+L$7:L14) -> 20686.529 | O14: =Inputs!B17 -> 0.065 | P14: =Inputs!B16 -> 0 | Q14: =(Q13+Projection!J12)*(1+O14) -> 20686.529 | R14: =Q14/PRODUCT(1+P$7:P14) -> 20686.529
A15: 8 | B15: 8 | C15: =Inputs!B17 -> 0.065 | D15: =Inputs!B16 -> 0 | E15: =(E14+Projection!J13)*(1+C15) -> 23839.343 | F15: =E15/(1+Inputs!B16)^(8+1) -> 23839.343 | G15: =Inputs!B17 -> 0.065 | H15: =Inputs!B16 -> 0 | I15: =(I14+Projection!J13)*(1+G15) -> 23839.343 | J15: =I15/PRODUCT(1+H$7:H15) -> 23839.343 | K15: =Inputs!B17 -> 0.065 | L15: =Inputs!B16 -> 0 | M15: =(M14+Projection!J13)*(1+K15) -> 23839.343 | N15: =M15/PRODUCT(1+L$7:L15) -> 23839.343 | O15: =Inputs!B17 -> 0.065 | P15: =Inputs!B16 -> 0 | Q15: =(Q14+Projection!J13)*(1+O15) -> 23839.343 | R15: =Q15/PRODUCT(1+P$7:P15) -> 23839.343
A16: 9 | B16: 9 | C16: =Inputs!B17 -> 0.065 | D16: =Inputs!B16 -> 0 | E16: =(E15+Projection!J14)*(1+C16) -> 27224.078 | F16: =E16/(1+Inputs!B16)^(9+1) -> 27224.078 | G16: =Inputs!B17 -> 0.065 | H16: =Inputs!B16 -> 0 | I16: =(I15+Projection!J14)*(1+G16) -> 27224.078 | J16: =I16/PRODUCT(1+H$7:H16) -> 27224.078 | K16: =Inputs!B17 -> 0.065 | L16: =Inputs!B16 -> 0 | M16: =(M15+Projection!J14)*(1+K16) -> 27224.078 | N16: =M16/PRODUCT(1+L$7:L16) -> 27224.078 | O16: =Inputs!B17 -> 0.065 | P16: =Inputs!B16 -> 0 | Q16: =(Q15+Projection!J14)*(1+O16) -> 27224.078 | R16: =Q16/PRODUCT(1+P$7:P16) -> 27224.078
A17: 10 | B17: 10 | C17: =Inputs!B17 -> 0.065 | D17: =Inputs!B16 -> 0 | E17: =(E16+Projection!J15)*(1+C17) -> 30856.212 | F17: =E17/(1+Inputs!B16)^(10+1) -> 30856.212 | G17: =Inputs!B17 -> 0.065 | H17: =Inputs!B16 -> 0 | I17: =(I16+Projection!J15)*(1+G17) -> 30856.212 | J17: =I17/PRODUCT(1+H$7:H17) -> 30856.212 | K17: =Inputs!B17 -> 0.065 | L17: =Inputs!B16 -> 0 | M17: =(M16+Projection!J15)*(1+K17) -> 30856.212 | N17: =M17/PRODUCT(1+L$7:L17) -> 30856.212 | O17: =Inputs!B17 -> 0.065 | P17: =Inputs!B16 -> 0 | Q17: =(Q16+Projection!J15)*(1+O17) -> 30856.212 | R17: =Q17/PRODUCT(1+P$7:P17) -> 30856.212
A18: 11 | B18: 11 | C18: =Inputs!B17 -> 0.065 | D18: =Inputs!B16 -> 0 | E18: =(E17+Projection!J16)*(1+C18) -> 34752.233 | F18: =E18/(1+Inputs!B16)^(11+1) -> 34752.233 | G18: =Inputs!B17 -> 0.065 | H18: =Inputs!B16 -> 0 | I18: =(I17+Projection!J16)*(1+G18) -> 34752.233 | J18: =I18/PRODUCT(1+H$7:H18) -> 34752.233 | K18: =Inputs!B17 -> 0.065 | L18: =Inputs!B16 -> 0 | M18: =(M17+Projection!J16)*(1+K18) -> 34752.233 | N18: =M18/PRODUCT(1+L$7:L18) -> 34752.233 | O18: =Inputs!B17 -> 0.065 | P18: =Inputs!B16 -> 0 | Q18: =(Q17+Projection!J16)*(1+O18) -> 34752.233 | R18: =Q18/PRODUCT(1+P$7:P18) -> 34752.233
A19: 12 | B19: 12 | C19: =Inputs!B17 -> 0.065 | D19: =Inputs!B16 -> 0 | E19: =(E18+Projection!J17)*(1+C19) -> 38929.711 | F19: =E19/(1+Inputs!B16)^(12+1) -> 38929.711 | G19: =Inputs!B17 -> 0.065 | H19: =Inputs!B16 -> 0 | I19: =(I18+Projection!J17)*(1+G19) -> 38929.711 | J19: =I19/PRODUCT(1+H$7:H19) -> 38929.711 | K19: =Inputs!B17 -> 0.065 | L19: =Inputs!B16 -> 0 | M19: =(M18+Projection!J17)*(1+K19) -> 38929.711 | N19: =M19/PRODUCT(1+L$7:L19) -> 38929.711 | O19: =Inputs!B17 -> 0.065 | P19: =Inputs!B16 -> 0 | Q19: =(Q18+Projection!J17)*(1+O19) -> 38929.711 | R19: =Q19/PRODUCT(1+P$7:P19) -> 38929.711
A20: 13 | B20: 13 | C20: =Inputs!B17 -> 0.065 | D20: =Inputs!B16 -> 0 | E20: =(E19+Projection!J18)*(1+C20) -> 43407.36 | F20: =E20/(1+Inputs!B16)^(13+1) -> 43407.36 | G20: =Inputs!B17 -> 0.065 | H20: =Inputs!B16 -> 0 | I20: =(I19+Projection!J18)*(1+G20) -> 43407.36 | J20: =I20/PRODUCT(1+H$7:H20) -> 43407.36 | K20: =Inputs!B17 -> 0.065 | L20: =Inputs!B16 -> 0 | M20: =(M19+Projection!J18)*(1+K20) -> 43407.36 | N20: =M20/PRODUCT(1+L$7:L20) -> 43407.36 | O20: =Inputs!B17 -> 0.065 | P20: =Inputs!B16 -> 0 | Q20: =(Q19+Projection!J18)*(1+O20) -> 43407.36 | R20: =Q20/PRODUCT(1+P$7:P20) -> 43407.36
A21: 14 | B21: 14 | C21: =Inputs!B17 -> 0.065 | D21: =Inputs!B16 -> 0 | E21: =(E20+Projection!J19)*(1+C21) -> 48205.12 | F21: =E21/(1+Inputs!B16)^(14+1) -> 48205.12 | G21: =Inputs!B17 -> 0.065 | H21: =Inputs!B16 -> 0 | I21: =(I20+Projection!J19)*(1+G21) -> 48205.12 | J21: =I21/PRODUCT(1+H$7:H21) -> 48205.12 | K21: =Inputs!B17 -> 0.065 | L21: =Inputs!B16 -> 0 | M21: =(M20+Projection!J19)*(1+K21) -> 48205.12 | N21: =M21/PRODUCT(1+L$7:L21) -> 48205.12 | O21: =Inputs!B17 -> 0.065 | P21: =Inputs!B16 -> 0 | Q21: =(Q20+Projection!J19)*(1+O21) -> 48205.12 | R21: =Q21/PRODUCT(1+P$7:P21) -> 48205.12
A22: 15 | B22: 15 | C22: =Inputs!B17 -> 0.065 | D22: =Inputs!B16 -> 0 | E22: =(E21+Projection!J20)*(1+C22) -> 53344.23 | F22: =E22/(1+Inputs!B16)^(15+1) -> 53344.23 | G22: =Inputs!B17 -> 0.065 | H22: =Inputs!B16 -> 0 | I22: =(I21+Projection!J20)*(1+G22) -> 53344.23 | J22: =I22/PRODUCT(1+H$7:H22) -> 53344.23 | K22: =Inputs!B17 -> 0.065 | L22: =Inputs!B16 -> 0 | M22: =(M21+Projection!J20)*(1+K22) -> 53344.23 | N22: =M22/PRODUCT(1+L$7:L22) -> 53344.23 | O22: =Inputs!B17 -> 0.065 | P22: =Inputs!B16 -> 0 | Q22: =(Q21+Projection!J20)*(1+O22) -> 53344.23 | R22: =Q22/PRODUCT(1+P$7:P22) -> 53344.23
A23: 16 | B23: 16 | C23: =Inputs!B17 -> 0.065 | D23: =Inputs!B16 -> 0 | E23: =(E22+Projection!J21)*(1+C23) -> 58847.32 | F23: =E23/(1+Inputs!B16)^(16+1) -> 58847.32 | G23: =Inputs!B17 -> 0.065 | H23: =Inputs!B16 -> 0 | I23: =(I22+Projection!J21)*(1+G23) -> 58847.32 | J23: =I23/PRODUCT(1+H$7:H23) -> 58847.32 | K23: =Inputs!B17 -> 0.065 | L23: =Inputs!B16 -> 0 | M23: =(M22+Projection!J21)*(1+K23) -> 58847.32 | N23: =M23/PRODUCT(1+L$7:L23) -> 58847.32 | O23: =Inputs!B17 -> 0.065 | P23: =Inputs!B16 -> 0 | Q23: =(Q22+Projection!J21)*(1+O23) -> 58847.32 | R23: =Q23/PRODUCT(1+P$7:P23) -> 58847.32
A24: 17 | B24: 17 | C24: =Inputs!B17 -> 0.065 | D24: =Inputs!B16 -> 0 | E24: =(E23+Projection!J22)*(1+C24) -> 64738.494 | F24: =E24/(1+Inputs!B16)^(17+1) -> 64738.494 | G24: =Inputs!B17 -> 0.065 | H24: =Inputs!B16 -> 0 | I24: =(I23+Projection!J22)*(1+G24) -> 64738.494 | J24: =I24/PRODUCT(1+H$7:H24) -> 64738.494 | K24: =Inputs!B17 -> 0.065 | L24: =Inputs!B16 -> 0 | M24: =(M23+Projection!J22)*(1+K24) -> 64738.494 | N24: =M24/PRODUCT(1+L$7:L24) -> 64738.494 | O24: =Inputs!B17 -> 0.065 | P24: =Inputs!B16 -> 0 | Q24: =(Q23+Projection!J22)*(1+O24) -> 64738.494 | R24: =Q24/PRODUCT(1+P$7:P24) -> 64738.494
A25: 18 | B25: 18 | C25: =Inputs!B17 -> 0.065 | D25: =Inputs!B16 -> 0 | E25: =(E24+Projection!J23)*(1+C25) -> 71043.432 | F25: =E25/(1+Inputs!B16)^(18+1) -> 71043.432 | G25: =Inputs!B17 -> 0.065 | H25: =Inputs!B16 -> 0 | I25: =(I24+Projection!J23)*(1+G25) -> 71043.432 | J25: =I25/PRODUCT(1+H$7:H25) -> 71043.432 | K25: =Inputs!B17 -> 0.065 | L25: =Inputs!B16 -> 0 | M25: =(M24+Projection!J23)*(1+K25) -> 71043.432 | N25: =M25/PRODUCT(1+L$7:L25) -> 71043.432 | O25: =Inputs!B17 -> 0.065 | P25: =Inputs!B16 -> 0 | Q25: =(Q24+Projection!J23)*(1+O25) -> 71043.432 | R25: =Q25/PRODUCT(1+P$7:P25) -> 71043.432
A26: 19 | B26: 19 | C26: =Inputs!B17 -> 0.065 | D26: =Inputs!B16 -> 0 | E26: =(E25+Projection!J24)*(1+C26) -> 77789.489 | F26: =E26/(1+Inputs!B16)^(19+1) -> 77789.489 | G26: =Inputs!B17 -> 0.065 | H26: =Inputs!B16 -> 0 | I26: =(I25+Projection!J24)*(1+G26) -> 77789.489 | J26: =I26/PRODUCT(1+H$7:H26) -> 77789.489 | K26: =Inputs!B17 -> 0.065 | L26: =Inputs!B16 -> 0 | M26: =(M25+Projection!J24)*(1+K26) -> 77789.489 | N26: =M26/PRODUCT(1+L$7:L26) -> 77789.489 | O26: =Inputs!B17 -> 0.065 | P26: =Inputs!B16 -> 0 | Q26: =(Q25+Projection!J24)*(1+O26) -> 77789.489 | R26: =Q26/PRODUCT(1+P$7:P26) -> 77789.489
A27: 20 | B27: 20 | C27: =Inputs!B17 -> 0.065 | D27: =Inputs!B16 -> 0 | E27: =(E26+Projection!J25)*(1+C27) -> 85005.804 | F27: =E27/(1+Inputs!B16)^(20+1) -> 85005.804 | G27: =Inputs!B17 -> 0.065 | H27: =Inputs!B16 -> 0 | I27: =(I26+Projection!J25)*(1+G27) -> 85005.804 | J27: =I27/PRODUCT(1+H$7:H27) -> 85005.804 | K27: =Inputs!B17 -> 0.065 | L27: =Inputs!B16 -> 0 | M27: =(M26+Projection!J25)*(1+K27) -> 85005.804 | N27: =M27/PRODUCT(1+L$7:L27) -> 85005.804 | O27: =Inputs!B17 -> 0.065 | P27: =Inputs!B16 -> 0 | Q27: =(Q26+Projection!J25)*(1+O27) -> 85005.804 | R27: =Q27/PRODUCT(1+P$7:P27) -> 85005.804
A28: 21 | B28: 21 | C28: =Inputs!B17 -> 0.065 | D28: =Inputs!B16 -> 0 | E28: =(E27+Projection!J26)*(1+C28) -> 92723.418 | F28: =E28/(1+Inputs!B16)^(21+1) -> 92723.418 | G28: =Inputs!B17 -> 0.065 | H28: =Inputs!B16 -> 0 | I28: =(I27+Projection!J26)*(1+G28) -> 92723.418 | J28: =I28/PRODUCT(1+H$7:H28) -> 92723.418 | K28: =Inputs!B17 -> 0.065 | L28: =Inputs!B16 -> 0 | M28: =(M27+Projection!J26)*(1+K28) -> 92723.418 | N28: =M28/PRODUCT(1+L$7:L28) -> 92723.418 | O28: =Inputs!B17 -> 0.065 | P28: =Inputs!B16 -> 0 | Q28: =(Q27+Projection!J26)*(1+O28) -> 92723.418 | R28: =Q28/PRODUCT(1+P$7:P28) -> 92723.418
A29: 22 | B29: 22 | C29: =Inputs!B17 -> 0.065 | D29: =Inputs!B16 -> 0 | E29: =(E28+Projection!J27)*(1+C29) -> 100975.4 | F29: =E29/(1+Inputs!B16)^(22+1) -> 100975.4 | G29: =Inputs!B17 -> 0.065 | H29: =Inputs!B16 -> 0 | I29: =(I28+Projection!J27)*(1+G29) -> 100975.4 | J29: =I29/PRODUCT(1+H$7:H29) -> 100975.4 | K29: =Inputs!B17 -> 0.065 | L29: =Inputs!B16 -> 0 | M29: =(M28+Projection!J27)*(1+K29) -> 100975.4 | N29: =M29/PRODUCT(1+L$7:L29) -> 100975.4 | O29: =Inputs!B17 -> 0.065 | P29: =Inputs!B16 -> 0 | Q29: =(Q28+Projection!J27)*(1+O29) -> 100975.4 | R29: =Q29/PRODUCT(1+P$7:P29) -> 100975.4
A30: 23 | B30: 23 | C30: =Inputs!B17 -> 0.065 | D30: =Inputs!B16 -> 0 | E30: =(E29+Projection!J28)*(1+C30) -> 109796.96 | F30: =E30/(1+Inputs!B16)^(23+1) -> 109796.96 | G30: =Inputs!B17 -> 0.065 | H30: =Inputs!B16 -> 0 | I30: =(I29+Projection!J28)*(1+G30) -> 109796.96 | J30: =I30/PRODUCT(1+H$7:H30) -> 109796.96 | K30: =Inputs!B17 -> 0.065 | L30: =Inputs!B16 -> 0 | M30: =(M29+Projection!J28)*(1+K30) -> 109796.96 | N30: =M30/PRODUCT(1+L$7:L30) -> 109796.96 | O30: =Inputs!B17 -> 0.065 | P30: =Inputs!B16 -> 0 | Q30: =(Q29+Projection!J28)*(1+O30) -> 109796.96 | R30: =Q30/PRODUCT(1+P$7:P30) -> 109796.96
A31: 24 | B31: 24 | C31: =Inputs!B17 -> 0.065 | D31: =Inputs!B16 -> 0 | E31: =(E30+Projection!J29)*(1+C31) -> 119225.63 | F31: =E31/(1+Inputs!B16)^(24+1) -> 119225.63 | G31: =Inputs!B17 -> 0.065 | H31: =Inputs!B16 -> 0 | I31: =(I30+Projection!J29)*(1+G31) -> 119225.63 | J31: =I31/PRODUCT(1+H$7:H31) -> 119225.63 | K31: =Inputs!B17 -> 0.065 | L31: =Inputs!B16 -> 0 | M31: =(M30+Projection!J29)*(1+K31) -> 119225.63 | N31: =M31/PRODUCT(1+L$7:L31) -> 119225.63 | O31: =Inputs!B17 -> 0.065 | P31: =Inputs!B16 -> 0 | Q31: =(Q30+Projection!J29)*(1+O31) -> 119225.63 | R31: =Q31/PRODUCT(1+P$7:P31) -> 119225.63
A32: 25 | B32: 25 | C32: =Inputs!B17 -> 0.065 | D32: =Inputs!B16 -> 0 | E32: =(E31+Projection!J30)*(1+C32) -> 129301.38 | F32: =E32/(1+Inputs!B16)^(25+1) -> 129301.38 | G32: -0.13 | H32: 0 | I32: =(I31+Projection!J30)*(1+G32) -> 105626.48 | J32: =I32/PRODUCT(1+H$7:H32) -> 105626.48 | K32: =Inputs!B17 -> 0.065 | L32: =Inputs!B16 -> 0 | M32: =(M31+Projection!J30)*(1+K32) -> 129301.38 | N32: =M32/PRODUCT(1+L$7:L32) -> 129301.38 | O32: =Inputs!B17 -> 0.065 | P32: =Inputs!B16 -> 0 | Q32: =(Q31+Projection!J30)*(1+O32) -> 129301.38 | R32: =Q32/PRODUCT(1+P$7:P32) -> 129301.38
A33: 26 | B33: 26 | C33: =Inputs!B17 -> 0.065 | D33: =Inputs!B16 -> 0 | E33: =(E32+Projection!J31)*(1+C33) -> 140066.76 | F33: =E33/(1+Inputs!B16)^(26+1) -> 140066.76 | G33: -0.3 | H33: -0.024 | I33: =(I32+Projection!J31)*(1+G33) -> 75490.229 | J33: =I33/PRODUCT(1+H$7:H33) -> 77346.546 | K33: =Inputs!B17 -> 0.065 | L33: =Inputs!B16 -> 0 | M33: =(M32+Projection!J31)*(1+K33) -> 140066.76 | N33: =M33/PRODUCT(1+L$7:L33) -> 140066.76 | O33: =Inputs!B17 -> 0.065 | P33: =Inputs!B16 -> 0 | Q33: =(Q32+Projection!J31)*(1+O33) -> 140066.76 | R33: =Q33/PRODUCT(1+P$7:P33) -> 140066.76
A34: 27 | B34: 27 | C34: =Inputs!B17 -> 0.065 | D34: =Inputs!B16 -> 0 | E34: =(E33+Projection!J32)*(1+C34) -> 151567.13 | F34: =E34/(1+Inputs!B16)^(27+1) -> 151567.13 | G34: -0.45 | H34: -0.09 | I34: =(I33+Projection!J32)*(1+G34) -> 42757.012 | J34: =I34/PRODUCT(1+H$7:H34) -> 46985.727 | K34: =Inputs!B17 -> 0.065 | L34: =Inputs!B16 -> 0 | M34: =(M33+Projection!J32)*(1+K34) -> 151567.13 | N34: =M34/PRODUCT(1+L$7:L34) -> 151567.13 | O34: =Inputs!B17 -> 0.065 | P34: =Inputs!B16 -> 0 | Q34: =(Q33+Projection!J32)*(1+O34) -> 151567.13 | R34: =Q34/PRODUCT(1+P$7:P34) -> 151567.13
A35: 28 | B35: 28 | C35: =Inputs!B17 -> 0.065 | D35: =Inputs!B16 -> 0 | E35: =(E34+Projection!J33)*(1+C35) -> 163850.78 | F35: =E35/(1+Inputs!B16)^(28+1) -> 163850.78 | G35: -0.1 | H35: -0.099 | I35: =(I34+Projection!J33)*(1+G35) -> 40536.345 | J35: =I35/PRODUCT(1+H$7:H35) -> 44990.394 | K35: =Inputs!B17 -> 0.065 | L35: =Inputs!B16 -> 0 | M35: =(M34+Projection!J33)*(1+K35) -> 163850.78 | N35: =M35/PRODUCT(1+L$7:L35) -> 163850.78 | O35: =Inputs!B17 -> 0.065 | P35: =Inputs!B16 -> 0 | Q35: =(Q34+Projection!J33)*(1+O35) -> 163850.78 | R35: =Q35/PRODUCT(1+P$7:P35) -> 163850.78
A36: 29 | B36: 29 | C36: =Inputs!B17 -> 0.065 | D36: =Inputs!B16 -> 0 | E36: =(E35+Projection!J34)*(1+C36) -> 176969.17 | F36: =E36/(1+Inputs!B16)^(29+1) -> 176969.17 | G36: 0.55 | H36: 0.008 | I36: =(I35+Projection!J34)*(1+G36) -> 66423.386 | J36: =I36/PRODUCT(1+H$7:H36) -> 65896.216 | K36: =Inputs!B17 -> 0.065 | L36: =Inputs!B16 -> 0 | M36: =(M35+Projection!J34)*(1+K36) -> 176969.17 | N36: =M36/PRODUCT(1+L$7:L36) -> 176969.17 | O36: =Inputs!B17 -> 0.065 | P36: =Inputs!B16 -> 0 | Q36: =(Q35+Projection!J34)*(1+O36) -> 176969.17 | R36: =Q36/PRODUCT(1+P$7:P36) -> 176969.17
A37: 30 | B37: 30 | C37: =Inputs!B17 -> 0.065 | D37: =Inputs!B16 -> 0 | E37: =(E36+Projection!J35)*(1+C37) -> 190977.09 | F37: =E37/(1+Inputs!B16)^(30+1) -> 190977.09 | G37: -0.02 | H37: 0.014 | I37: =(I36+Projection!J35)*(1+G37) -> 67399.918 | J37: =I37/PRODUCT(1+H$7:H37) -> 66469.347 | K37: -0.1 | L37: 0.029 | M37: =(M36+Projection!J35)*(1+K37) -> 161389.09 | N37: =M37/PRODUCT(1+L$7:L37) -> 156840.71 | O37: =Inputs!B17 -> 0.065 | P37: =Inputs!B16 -> 0 | Q37: =(Q36+Projection!J35)*(1+O37) -> 190977.09 | R37: =Q37/PRODUCT(1+P$7:P37) -> 190977.09
A38: 31 | B38: 31 | C38: =Inputs!B17 -> 0.065 | D38: =Inputs!B16 -> 0 | E38: =(E37+Projection!J36)*(1+C38) -> 205932.91 | F38: =E38/(1+Inputs!B16)^(31+1) -> 205932.91 | G38: 0.46 | H38: 0.029 | I38: =(I37+Projection!J36)*(1+G38) -> 101889.11 | J38: =I38/PRODUCT(1+H$7:H38) -> 99017.603 | K38: 0.24 | L38: 0.031 | M38: =(M37+Projection!J36)*(1+K38) -> 203082.53 | N38: =M38/PRODUCT(1+L$7:L38) -> 196976.27 | O38: =Inputs!B17 -> 0.065 | P38: =Inputs!B16 -> 0 | Q38: =(Q37+Projection!J36)*(1+O38) -> 205932.91 | R38: =Q38/PRODUCT(1+P$7:P38) -> 205932.91
A39: 32 | B39: 32 | C39: =Inputs!B17 -> 0.065 | D39: =Inputs!B16 -> 0 | E39: =(E38+Projection!J37)*(1+C39) -> 221898.8 | F39: =E39/(1+Inputs!B16)^(32+1) -> 221898.8 | G39: 0.32 | H39: 0.012 | I39: =(I38+Projection!J37)*(1+G39) -> 137691.69 | J39: =I39/PRODUCT(1+H$7:H39) -> 136058.98 | K39: 0.11 | L39: 0.044 | M39: =(M38+Projection!J37)*(1+K39) -> 228110.89 | N39: =M39/PRODUCT(1+L$7:L39) -> 218497.02 | O39: =Inputs!B17 -> 0.065 | P39: =Inputs!B16 -> 0 | Q39: =(Q38+Projection!J37)*(1+O39) -> 221898.8 | R39: =Q39/PRODUCT(1+P$7:P39) -> 221898.8
A40: 33 | B40: 33 | C40: =Inputs!B17 -> 0.065 | D40: =Inputs!B16 -> 0 | E40: =(E39+Projection!J38)*(1+C40) -> 238940.99 | F40: =E40/(1+Inputs!B16)^(33+1) -> 238940.99 | G40: -0.36 | H40: 0.029 | I40: =(I39+Projection!J38)*(1+G40) -> 89696.402 | J40: =I40/PRODUCT(1+H$7:H40) -> 87168.515 | K40: -0.08 | L40: 0.054 | M40: =(M39+Projection!J38)*(1+K40) -> 212124.24 | N40: =M40/PRODUCT(1+L$7:L40) -> 201256.39 | O40: =Inputs!B17 -> 0.065 | P40: =Inputs!B16 -> 0 | Q40: =(Q39+Projection!J38)*(1+O40) -> 238940.99 | R40: =Q40/PRODUCT(1+P$7:P40) -> 238940.99
A41: 34 | B41: 34 | C41: =Inputs!B17 -> 0.065 | D41: =Inputs!B16 -> 0 | E41: =(E40+Projection!J39)*(1+C41) -> 257130.01 | F41: =E41/(1+Inputs!B16)^(34+1) -> 257130.01 | G41: 0.3 | H41: -0.02 | I41: =(I40+Projection!J39)*(1+G41) -> 119849.65 | J41: =I41/PRODUCT(1+H$7:H41) -> 122295.56 | K41: 0.04 | L41: 0.058 | M41: =(M40+Projection!J39)*(1+K41) -> 223204.67 | N41: =M41/PRODUCT(1+L$7:L41) -> 210968.5 | O41: =Inputs!B17 -> 0.065 | P41: =Inputs!B16 -> 0 | Q41: =(Q40+Projection!J39)*(1+O41) -> 257130.01 | R41: =Q41/PRODUCT(1+P$7:P41) -> 257130.01
A42: 35 | B42: 35 | C42: =Inputs!B17 -> 0.065 | D42: =Inputs!B16 -> 0 | E42: =(E41+Projection!J40)*(1+C42) -> 276540.98 | F42: =E42/(1+Inputs!B16)^(35+1) -> 276540.98 | G42: 0 | H42: -0.005 | I42: =(I41+Projection!J40)*(1+G42) -> 122382.53 | J42: =I42/PRODUCT(1+H$7:H42) -> 122997.52 | K42: 0.14 | L42: 0.043 | M42: =(M41+Projection!J40)*(1+K42) -> 257340.81 | N42: =M42/PRODUCT(1+L$7:L42) -> 246731.37 | O42: -0.09 | P42: 0.034 | Q42: =(Q41+Projection!J40)*(1+O42) -> 236293.23 | R42: =Q42/PRODUCT(1+P$7:P42) -> 228523.44
A43: 36 | B43: 36 | C43: =Inputs!B17 -> 0.065 | D43: =Inputs!B16 -> 0 | E43: =(E42+Projection!J41)*(1+C43) -> 297253.93 | F43: =E43/(1+Inputs!B16)^(36+1) -> 297253.93 | G43: -0.1 | H43: 0.01 | I43: =(I42+Projection!J41)*(1+G43) -> 112457.9 | J43: =I43/PRODUCT(1+H$7:H43) -> 111344.46 | K43: 0.19 | L43: 0.033 | M43: =(M42+Projection!J41)*(1+K43) -> 309294.69 | N43: =M43/PRODUCT(1+L$7:L43) -> 299414.03 | O43: -0.12 | P43: 0.028 | Q43: =(Q42+Projection!J41)*(1+O43) -> 210200.25 | R43: =Q43/PRODUCT(1+P$7:P43) -> 204474.95
A44: 37 | B44: 37 | C44: =Inputs!B17 -> 0.065 | D44: =Inputs!B16 -> 0 | E44: =(E43+Projection!J42)*(1+C44) -> 319354.08 | F44: =E44/(1+Inputs!B16)^(37+1) -> 319354.08 | G44: -0.13 | H44: 0.097 | I44: =(I43+Projection!J42)*(1+G44) -> 100108.25 | J44: =I44/PRODUCT(1+H$7:H44) -> 91256.384 | K44: -0.15 | L44: 0.062 | M44: =(M43+Projection!J42)*(1+K44) -> 265118.18 | N44: =M44/PRODUCT(1+L$7:L44) -> 249640.47 | O44: -0.22 | P44: 0.016 | Q44: =(Q43+Projection!J42)*(1+O44) -> 165991.26 | R44: =Q44/PRODUCT(1+P$7:P44) -> 163377.23
A45: 38 | B45: 38 | C45: =Inputs!B17 -> 0.065 | D45: =Inputs!B16 -> 0 | E45: =(E44+Projection!J43)*(1+C45) -> 342932.22 | F45: =E45/(1+Inputs!B16)^(38+1) -> 342932.22 | G45: 0.2 | H45: 0.092 | I45: =(I44+Projection!J43)*(1+G45) -> 123307.5 | J45: =I45/PRODUCT(1+H$7:H45) -> 112918.96 | K45: -0.27 | L45: 0.11 | M45: =(M44+Projection!J43)*(1+K45) -> 195469.31 | N45: =M45/PRODUCT(1+L$7:L45) -> 176098.48 | O45: 0.29 | P45: 0.023 | Q45: =(Q44+Projection!J43)*(1+O45) -> 217544.65 | R45: =Q45/PRODUCT(1+P$7:P45) -> 212653.61
A46: 39 | B46: 39 | C46: =Inputs!B17 -> 0.065 | D46: =Inputs!B16 -> 0 | E46: =(E45+Projection!J44)*(1+C46) -> 368085.02 | F46: =E46/(1+Inputs!B16)^(39+1) -> 368085.02 | G46: 0.26 | H46: 0.03 | I46: =(I45+Projection!J44)*(1+G46) -> 158753.73 | J46: =I46/PRODUCT(1+H$7:H46) -> 154129.83 | K46: 0.37 | L46: 0.091 | M46: =(M45+Projection!J44)*(1+K46) -> 271474.86 | N46: =M46/PRODUCT(1+L$7:L46) -> 248831.22 | O46: 0.11 | P46: 0.027 | Q46: =(Q45+Projection!J44)*(1+O46) -> 244457.71 | R46: =Q46/PRODUCT(1+P$7:P46) -> 238030.87
A47: 40 | B47: 40 | C47: =Inputs!B17 -> 0.065 | D47: =Inputs!B16 -> 0 | E47: =(E46+Projection!J45)*(1+C47) -> 394915.48 | F47: =E47/(1+Inputs!B16)^(40+1) -> 394915.48 | G47: 0.2 | H47: 0.019 | I47: =(I46+Projection!J45)*(1+G47) -> 193777.64 | J47: =I47/PRODUCT(1+H$7:H47) -> 190164.51 | K47: 0.24 | L47: 0.058 | M47: =(M46+Projection!J45)*(1+K47) -> 340011.09 | N47: =M47/PRODUCT(1+L$7:L47) -> 321371.54 | O47: 0.05 | P47: 0.034 | Q47: =(Q46+Projection!J45)*(1+O47) -> 259544.61 | R47: =Q47/PRODUCT(1+P$7:P47) -> 251010.26
A48: 41 | B48: 41 | C48: =Inputs!B17 -> 0.065 | D48: =Inputs!B16 -> 0 | E48: =(E47+Projection!J46)*(1+C48) -> 423533.27 | F48: =E48/(1+Inputs!B16)^(41+1) -> 423533.27 | G48: =Inputs!B17 -> 0.065 | H48: =Inputs!B16 -> 0 | I48: =(I47+Projection!J46)*(1+G48) -> 209321.47 | J48: =I48/PRODUCT(1+H$7:H48) -> 209321.47 | K48: -0.07 | L48: 0.065 | M48: =(M47+Projection!J46)*(1+K48) -> 318784.88 | N48: =M48/PRODUCT(1+L$7:L48) -> 299328.52 | O48: 0.16 | P48: 0.032 | Q48: =(Q47+Projection!J46)*(1+O48) -> 304283.02 | R48: =Q48/PRODUCT(1+P$7:P48) -> 294847.89
A49: 42 | B49: 42 | C49: =Inputs!B17 -> 0.065 | D49: =Inputs!B16 -> 0 | E49: =(E48+Projection!J47)*(1+C49) -> 454055.22 | F49: =E49/(1+Inputs!B16)^(42+1) -> 454055.22 | G49: =Inputs!B17 -> 0.065 | H49: =Inputs!B16 -> 0 | I49: =(I48+Projection!J47)*(1+G49) -> 225919.65 | J49: =I49/PRODUCT(1+H$7:H49) -> 225919.65 | K49: 0.07 | L49: 0.076 | M49: =(M48+Projection!J47)*(1+K49) -> 344106.16 | N49: =M49/PRODUCT(1+L$7:L49) -> 319801.26 | O49: 0.05 | P49: 0.028 | Q49: =(Q48+Projection!J47)*(1+O49) -> 322447.32 | R49: =Q49/PRODUCT(1+P$7:P49) -> 313664.71
A50: 43 | B50: 43 | C50: =Inputs!B17 -> 0.065 | D50: =Inputs!B16 -> 0 | E50: =(E49+Projection!J48)*(1+C50) -> 486605.76 | F50: =E50/(1+Inputs!B16)^(43+1) -> 486605.76 | G50: =Inputs!B17 -> 0.065 | H50: =Inputs!B16 -> 0 | I50: =(I49+Projection!J48)*(1+G50) -> 243641.38 | J50: =I50/PRODUCT(1+H$7:H50) -> 243641.38 | K50: 0.18 | L50: 0.114 | M50: =(M49+Projection!J48)*(1+K50) -> 409410.15 | N50: =M50/PRODUCT(1+L$7:L50) -> 367513.6 | O50: -0.37 | P50: 0.038 | Q50: =(Q49+Projection!J48)*(1+O50) -> 204938.32 | R50: =Q50/PRODUCT(1+P$7:P50) -> 197435.76
A51: 44 | B51: 44 | C51: =Inputs!B17 -> 0.065 | D51: =Inputs!B16 -> 0 | E51: =(E50+Projection!J49)*(1+C51) -> 521317.42 | F51: =E51/(1+Inputs!B16)^(44+1) -> 521317.42 | G51: =Inputs!B17 -> 0.065 | H51: =Inputs!B16 -> 0 | I51: =(I50+Projection!J49)*(1+G51) -> 262560.35 | J51: =I51/PRODUCT(1+H$7:H51) -> 262560.35 | K51: 0.32 | L51: 0.135 | M51: =(M50+Projection!J49)*(1+K51) -> 544241.69 | N51: =M51/PRODUCT(1+L$7:L51) -> 479508.1 | O51: 0.26 | P51: -0.004 | Q51: =(Q50+Projection!J49)*(1+O51) -> 261868.92 | R51: =Q51/PRODUCT(1+P$7:P51) -> 262920.6
A52: 45 | B52: 45 | C52: =Inputs!B17 -> 0.065 | D52: =Inputs!B16 -> 0 | E52: =(E51+Projection!J50)*(1+C52) -> 558331.33 | F52: =E52/(1+Inputs!B16)^(45+1) -> 558331.33 | G52: =Inputs!B17 -> 0.065 | H52: =Inputs!B16 -> 0 | I52: =(I51+Projection!J50)*(1+G52) -> 282755.06 | J52: =I52/PRODUCT(1+H$7:H52) -> 282755.06 | K52: -0.05 | L52: 0.103 | M52: =(M51+Projection!J50)*(1+K52) -> 519820.09 | N52: =M52/PRODUCT(1+L$7:L52) -> 471278.42 | O52: =Inputs!B17 -> 0.065 | P52: =Inputs!B16 -> 0 | Q52: =(Q51+Projection!J50)*(1+O52) -> 282018.68 | R52: =Q52/PRODUCT(1+P$7:P52) -> 282018.68
A53: 46 | B53: 46 | C53: =Inputs!B17 -> 0.065 | D53: =Inputs!B16 -> 0 | E53: =(E52+Projection!J51)*(1+C53) -> 597797.84 | F53: =E53/(1+Inputs!B16)^(46+1) -> 597797.84 | G53: =Inputs!B17 -> 0.065 | H53: =Inputs!B16 -> 0 | I53: =(I52+Projection!J51)*(1+G53) -> 304309.11 | J53: =I53/PRODUCT(1+H$7:H53) -> 304309.11 | K53: 0.21 | L53: 0.061 | M53: =(M52+Projection!J51)*(1+K53) -> 632589.56 | N53: =M53/PRODUCT(1+L$7:L53) -> 596220.13 | O53: =Inputs!B17 -> 0.065 | P53: =Inputs!B16 -> 0 | Q53: =(Q52+Projection!J51)*(1+O53) -> 303524.87 | R53: =Q53/PRODUCT(1+P$7:P53) -> 303524.87
A54: 47 | B54: 47 | C54: =Inputs!B17 -> 0.065 | D54: =Inputs!B16 -> 0 | E54: =(E53+Projection!J52)*(1+C54) -> 639877.06 | F54: =E54/(1+Inputs!B16)^(47+1) -> 639877.06 | G54: =Inputs!B17 -> 0.065 | H54: =Inputs!B16 -> 0 | I54: =(I53+Projection!J52)*(1+G54) -> 327311.57 | J54: =I54/PRODUCT(1+H$7:H54) -> 327311.57 | K54: =Inputs!B17 -> 0.065 | L54: =Inputs!B16 -> 0 | M54: =(M53+Projection!J52)*(1+K54) -> 676930.24 | N54: =M54/PRODUCT(1+L$7:L54) -> 676930.24 | O54: =Inputs!B17 -> 0.065 | P54: =Inputs!B16 -> 0 | Q54: =(Q53+Projection!J52)*(1+O54) -> 326476.35 | R54: =Q54/PRODUCT(1+P$7:P54) -> 326476.35
A55: 48 | B55: 48 | C55: =Inputs!B17 -> 0.065 | D55: =Inputs!B16 -> 0 | E55: =(E54+Projection!J53)*(1+C55) -> 684739.53 | F55: =E55/(1+Inputs!B16)^(48+1) -> 684739.53 | G55: =Inputs!B17 -> 0.065 | H55: =Inputs!B16 -> 0 | I55: =(I54+Projection!J53)*(1+G55) -> 351857.28 | J55: =I55/PRODUCT(1+H$7:H55) -> 351857.28 | K55: =Inputs!B17 -> 0.065 | L55: =Inputs!B16 -> 0 | M55: =(M54+Projection!J53)*(1+K55) -> 724201.17 | N55: =M55/PRODUCT(1+L$7:L55) -> 724201.17 | O55: =Inputs!B17 -> 0.065 | P55: =Inputs!B16 -> 0 | Q55: =(Q54+Projection!J53)*(1+O55) -> 350967.77 | R55: =Q55/PRODUCT(1+P$7:P55) -> 350967.77
A56: 49 | B56: 49 | C56: =Inputs!B17 -> 0.065 | D56: =Inputs!B16 -> 0 | E56: =(E55+Projection!J54)*(1+C56) -> 732566.87 | F56: =E56/(1+Inputs!B16)^(49+1) -> 732566.87 | G56: =Inputs!B17 -> 0.065 | H56: =Inputs!B16 -> 0 | I56: =(I55+Projection!J54)*(1+G56) -> 378047.27 | J56: =I56/PRODUCT(1+H$7:H56) -> 378047.27 | K56: =Inputs!B17 -> 0.065 | L56: =Inputs!B16 -> 0 | M56: =(M55+Projection!J54)*(1+K56) -> 774593.51 | N56: =M56/PRODUCT(1+L$7:L56) -> 774593.51 | O56: =Inputs!B17 -> 0.065 | P56: =Inputs!B16 -> 0 | Q56: =(Q55+Projection!J54)*(1+O56) -> 377099.94 | R56: =Q56/PRODUCT(1+P$7:P56) -> 377099.94
A57: 50 | B57: 50 | C57: =Inputs!B17 -> 0.065 | D57: =Inputs!B16 -> 0 | E57: =(E56+Projection!J55)*(1+C57) -> 783552.53 | F57: =E57/(1+Inputs!B16)^(50+1) -> 783552.53 | G57: =Inputs!B17 -> 0.065 | H57: =Inputs!B16 -> 0 | I57: =(I56+Projection!J55)*(1+G57) -> 405989.15 | J57: =I57/PRODUCT(1+H$7:H57) -> 405989.15 | K57: =Inputs!B17 -> 0.065 | L57: =Inputs!B16 -> 0 | M57: =(M56+Projection!J55)*(1+K57) -> 828310.9 | N57: =M57/PRODUCT(1+L$7:L57) -> 828310.9 | O57: =Inputs!B17 -> 0.065 | P57: =Inputs!B16 -> 0 | Q57: =(Q56+Projection!J55)*(1+O57) -> 404980.25 | R57: =Q57/PRODUCT(1+P$7:P57) -> 404980.25
A58: 51 | B58: 51 | C58: =Inputs!B17 -> 0.065 | D58: =Inputs!B16 -> 0 | E58: =(E57+Projection!J56)*(1+C58) -> 837902.53 | F58: =E58/(1+Inputs!B16)^(51+1) -> 837902.53 | G58: =Inputs!B17 -> 0.065 | H58: =Inputs!B16 -> 0 | I58: =(I57+Projection!J56)*(1+G58) -> 435797.54 | J58: =I58/PRODUCT(1+H$7:H58) -> 435797.54 | K58: =Inputs!B17 -> 0.065 | L58: =Inputs!B16 -> 0 | M58: =(M57+Projection!J56)*(1+K58) -> 885570.2 | N58: =M58/PRODUCT(1+L$7:L58) -> 885570.2 | O58: =Inputs!B17 -> 0.065 | P58: =Inputs!B16 -> 0 | Q58: =(Q57+Projection!J56)*(1+O58) -> 434723.06 | R58: =Q58/PRODUCT(1+P$7:P58) -> 434723.06
A59: 52 | B59: 52 | C59: =Inputs!B17 -> 0.065 | D59: =Inputs!B16 -> 0 | E59: =(E58+Projection!J57)*(1+C59) -> 895836.32 | F59: =E59/(1+Inputs!B16)^(52+1) -> 895836.32 | G59: =Inputs!B17 -> 0.065 | H59: =Inputs!B16 -> 0 | I59: =(I58+Projection!J57)*(1+G59) -> 467594.5 | J59: =I59/PRODUCT(1+H$7:H59) -> 467594.5 | K59: =Inputs!B17 -> 0.065 | L59: =Inputs!B16 -> 0 | M59: =(M58+Projection!J57)*(1+K59) -> 946602.39 | N59: =M59/PRODUCT(1+L$7:L59) -> 946602.39 | O59: =Inputs!B17 -> 0.065 | P59: =Inputs!B16 -> 0 | Q59: =(Q58+Projection!J57)*(1+O59) -> 466450.18 | R59: =Q59/PRODUCT(1+P$7:P59) -> 466450.18
A60: 53 | B60: 53 | C60: =Inputs!B17 -> 0.065 | D60: =Inputs!B16 -> 0 | E60: =(E59+Projection!J58)*(1+C60) -> 957587.6 | F60: =E60/(1+Inputs!B16)^(53+1) -> 957587.6 | G60: =Inputs!B17 -> 0.065 | H60: =Inputs!B16 -> 0 | I60: =(I59+Projection!J58)*(1+G60) -> 501510.06 | J60: =I60/PRODUCT(1+H$7:H60) -> 501510.06 | K60: =Inputs!B17 -> 0.065 | L60: =Inputs!B16 -> 0 | M60: =(M59+Projection!J58)*(1+K60) -> 1011653.5 | N60: =M60/PRODUCT(1+L$7:L60) -> 1011653.5 | O60: =Inputs!B17 -> 0.065 | P60: =Inputs!B16 -> 0 | Q60: =(Q59+Projection!J58)*(1+O60) -> 500291.36 | R60: =Q60/PRODUCT(1+P$7:P60) -> 500291.36
A61: 54 | B61: 54 | C61: =Inputs!B17 -> 0.065 | D61: =Inputs!B16 -> 0 | E61: =(E60+Projection!J59)*(1+C61) -> 1023405.3 | F61: =E61/(1+Inputs!B16)^(54+1) -> 1023405.3 | G61: =Inputs!B17 -> 0.065 | H61: =Inputs!B16 -> 0 | I61: =(I60+Projection!J59)*(1+G61) -> 537682.7 | J61: =I61/PRODUCT(1+H$7:H61) -> 537682.7 | K61: =Inputs!B17 -> 0.065 | L61: =Inputs!B16 -> 0 | M61: =(M60+Projection!J59)*(1+K61) -> 1080985.4 | N61: =M61/PRODUCT(1+L$7:L61) -> 1080985.4 | O61: =Inputs!B17 -> 0.065 | P61: =Inputs!B16 -> 0 | Q61: =(Q60+Projection!J59)*(1+O61) -> 536384.78 | R61: =Q61/PRODUCT(1+P$7:P61) -> 536384.78
A62: 55 | B62: 55 | C62: =Inputs!B17 -> 0.065 | D62: =Inputs!B16 -> 0 | E62: =(E61+Projection!J60)*(1+C62) -> 1093554.4 | F62: =E62/(1+Inputs!B16)^(55+1) -> 1093554.4 | G62: =Inputs!B17 -> 0.065 | H62: =Inputs!B16 -> 0 | I62: =(I61+Projection!J60)*(1+G62) -> 576259.9 | J62: =I62/PRODUCT(1+H$7:H62) -> 576259.9 | K62: =Inputs!B17 -> 0.065 | L62: =Inputs!B16 -> 0 | M62: =(M61+Projection!J60)*(1+K62) -> 1154877.3 | N62: =M62/PRODUCT(1+L$7:L62) -> 1154877.3 | O62: =Inputs!B17 -> 0.065 | P62: =Inputs!B16 -> 0 | Q62: =(Q61+Projection!J60)*(1+O62) -> 574877.62 | R62: =Q62/PRODUCT(1+P$7:P62) -> 574877.62
A63: 56 | B63: 56 | C63: =Inputs!B17 -> 0.065 | D63: =Inputs!B16 -> 0 | E63: =(E62+Projection!J61)*(1+C63) -> 1168317.5 | F63: =E63/(1+Inputs!B16)^(56+1) -> 1168317.5 | G63: =Inputs!B17 -> 0.065 | H63: =Inputs!B16 -> 0 | I63: =(I62+Projection!J61)*(1+G63) -> 617398.78 | J63: =I63/PRODUCT(1+H$7:H63) -> 617398.78 | K63: =Inputs!B17 -> 0.065 | L63: =Inputs!B16 -> 0 | M63: =(M62+Projection!J61)*(1+K63) -> 1233626.3 | N63: =M63/PRODUCT(1+L$7:L63) -> 1233626.3 | O63: =Inputs!B17 -> 0.065 | P63: =Inputs!B16 -> 0 | Q63: =(Q62+Projection!J61)*(1+O63) -> 615926.65 | R63: =Q63/PRODUCT(1+P$7:P63) -> 615926.65
A64: 57 | B64: 57 | C64: =Inputs!B17 -> 0.065 | D64: =Inputs!B16 -> 0 | E64: =(E63+Projection!J62)*(1+C64) -> 1247995 | F64: =E64/(1+Inputs!B16)^(57+1) -> 1247995 | G64: =Inputs!B17 -> 0.065 | H64: =Inputs!B16 -> 0 | I64: =(I63+Projection!J62)*(1+G64) -> 661266.63 | J64: =I64/PRODUCT(1+H$7:H64) -> 661266.63 | K64: =Inputs!B17 -> 0.065 | L64: =Inputs!B16 -> 0 | M64: =(M63+Projection!J62)*(1+K64) -> 1317548.9 | N64: =M64/PRODUCT(1+L$7:L64) -> 1317548.9 | O64: =Inputs!B17 -> 0.065 | P64: =Inputs!B16 -> 0 | Q64: =(Q63+Projection!J62)*(1+O64) -> 659698.81 | R64: =Q64/PRODUCT(1+P$7:P64) -> 659698.81
A65: 58 | B65: 58 | C65: =Inputs!B17 -> 0.065 | D65: =Inputs!B16 -> 0 | E65: =(E64+Projection!J63)*(1+C65) -> 1332907.4 | F65: =E65/(1+Inputs!B16)^(58+1) -> 1332907.4 | G65: =Inputs!B17 -> 0.065 | H65: =Inputs!B16 -> 0 | I65: =(I64+Projection!J63)*(1+G65) -> 708041.67 | J65: =I65/PRODUCT(1+H$7:H65) -> 708041.67 | K65: =Inputs!B17 -> 0.065 | L65: =Inputs!B16 -> 0 | M65: =(M64+Projection!J63)*(1+K65) -> 1406982.3 | N65: =M65/PRODUCT(1+L$7:L65) -> 1406982.3 | O65: =Inputs!B17 -> 0.065 | P65: =Inputs!B16 -> 0 | Q65: =(Q64+Projection!J63)*(1+O65) -> 706371.95 | R65: =Q65/PRODUCT(1+P$7:P65) -> 706371.95
A66: 59 | B66: 59 | C66: =Inputs!B17 -> 0.065 | D66: =Inputs!B16 -> 0 | E66: =(E65+Projection!J64)*(1+C66) -> 1423395.7 | F66: =E66/(1+Inputs!B16)^(59+1) -> 1423395.7 | G66: =Inputs!B17 -> 0.065 | H66: =Inputs!B16 -> 0 | I66: =(I65+Projection!J64)*(1+G66) -> 757913.7 | J66: =I66/PRODUCT(1+H$7:H66) -> 757913.7 | K66: =Inputs!B17 -> 0.065 | L66: =Inputs!B16 -> 0 | M66: =(M65+Projection!J64)*(1+K66) -> 1502285.5 | N66: =M66/PRODUCT(1+L$7:L66) -> 1502285.5 | O66: =Inputs!B17 -> 0.065 | P66: =Inputs!B16 -> 0 | Q66: =(Q65+Projection!J64)*(1+O66) -> 756135.44 | R66: =Q66/PRODUCT(1+P$7:P66) -> 756135.44
A67: 60 | B67: 60 | C67: =Inputs!B17 -> 0.065 | D67: =Inputs!B16 -> 0 | E67: =(E66+Projection!J65)*(1+C67) -> 1519823.2 | F67: =E67/(1+Inputs!B16)^(60+1) -> 1519823.2 | G67: =Inputs!B17 -> 0.065 | H67: =Inputs!B16 -> 0 | I67: =(I66+Projection!J65)*(1+G67) -> 811084.86 | J67: =I67/PRODUCT(1+H$7:H67) -> 811084.86 | K67: =Inputs!B17 -> 0.065 | L67: =Inputs!B16 -> 0 | M67: =(M66+Projection!J65)*(1+K67) -> 1603840.8 | N67: =M67/PRODUCT(1+L$7:L67) -> 1603840.8 | O67: =Inputs!B17 -> 0.065 | P67: =Inputs!B16 -> 0 | Q67: =(Q66+Projection!J65)*(1+O67) -> 809191.01 | R67: =Q67/PRODUCT(1+P$7:P67) -> 809191.01
A68: 61 | B68: 61 | C68: =Inputs!B17 -> 0.065 | D68: =Inputs!B16 -> 0 | E68: =(E67+Projection!J66)*(1+C68) -> 1622576.8 | F68: =E68/(1+Inputs!B16)^(61+1) -> 1622576.8 | G68: =Inputs!B17 -> 0.065 | H68: =Inputs!B16 -> 0 | I68: =(I67+Projection!J66)*(1+G68) -> 867770.45 | J68: =I68/PRODUCT(1+H$7:H68) -> 867770.45 | K68: =Inputs!B17 -> 0.065 | L68: =Inputs!B16 -> 0 | M68: =(M67+Projection!J66)*(1+K68) -> 1712055.6 | N68: =M68/PRODUCT(1+L$7:L68) -> 1712055.6 | O68: =Inputs!B17 -> 0.065 | P68: =Inputs!B16 -> 0 | Q68: =(Q67+Projection!J66)*(1+O68) -> 865753.51 | R68: =Q68/PRODUCT(1+P$7:P68) -> 865753.51
A69: 62 | B69: 62 | C69: =Inputs!B17 -> 0.065 | D69: =Inputs!B16 -> 0 | E69: =(E68+Projection!J67)*(1+C69) -> 1732068.6 | F69: =E69/(1+Inputs!B16)^(62+1) -> 1732068.6 | G69: =Inputs!B17 -> 0.065 | H69: =Inputs!B16 -> 0 | I69: =(I68+Projection!J67)*(1+G69) -> 928199.79 | J69: =I69/PRODUCT(1+H$7:H69) -> 928199.79 | K69: =Inputs!B17 -> 0.065 | L69: =Inputs!B16 -> 0 | M69: =(M68+Projection!J67)*(1+K69) -> 1827363.4 | N69: =M69/PRODUCT(1+L$7:L69) -> 1827363.4 | O69: =Inputs!B17 -> 0.065 | P69: =Inputs!B16 -> 0 | Q69: =(Q68+Projection!J67)*(1+O69) -> 926051.75 | R69: =Q69/PRODUCT(1+P$7:P69) -> 926051.75
A70: 63 | B70: 63 | C70: =Inputs!B17 -> 0.065 | D70: =Inputs!B16 -> 0 | E70: =(E69+Projection!J68)*(1+C70) -> 1848737.3 | F70: =E70/(1+Inputs!B16)^(63+1) -> 1848737.3 | G70: =Inputs!B17 -> 0.065 | H70: =Inputs!B16 -> 0 | I70: =(I69+Projection!J68)*(1+G70) -> 992617.1 | J70: =I70/PRODUCT(1+H$7:H70) -> 992617.1 | K70: =Inputs!B17 -> 0.065 | L70: =Inputs!B16 -> 0 | M70: =(M69+Projection!J68)*(1+K70) -> 1950226.4 | N70: =M70/PRODUCT(1+L$7:L70) -> 1950226.4 | O70: =Inputs!B17 -> 0.065 | P70: =Inputs!B16 -> 0 | Q70: =(Q69+Projection!J68)*(1+O70) -> 990329.43 | R70: =Q70/PRODUCT(1+P$7:P70) -> 990329.43
A71: 64 | B71: 64 | C71: =Inputs!B17 -> 0.065 | D71: =Inputs!B16 -> 0 | E71: =(E70+Projection!J69)*(1+C71) -> 1973050.5 | F71: =E71/(1+Inputs!B16)^(64+1) -> 1973050.5 | G71: =Inputs!B17 -> 0.065 | H71: =Inputs!B16 -> 0 | I71: =(I70+Projection!J69)*(1+G71) -> 1061282.5 | J71: =I71/PRODUCT(1+H$7:H71) -> 1061282.5 | K71: =Inputs!B17 -> 0.065 | L71: =Inputs!B16 -> 0 | M71: =(M70+Projection!J69)*(1+K71) -> 2081136.4 | N71: =M71/PRODUCT(1+L$7:L71) -> 2081136.4 | O71: =Inputs!B17 -> 0.065 | P71: =Inputs!B16 -> 0 | Q71: =(Q70+Projection!J69)*(1+O71) -> 1058846.1 | R71: =Q71/PRODUCT(1+P$7:P71) -> 1058846.1
A72: 65 | B72: 65 | C72: =Inputs!B17 -> 0.065 | D72: =Inputs!B16 -> 0 | E72: =(E71+Projection!J70)*(1+C72) -> 2105506 | F72: =E72/(1+Inputs!B16)^(65+1) -> 2105506 | G72: =Inputs!B17 -> 0.065 | H72: =Inputs!B16 -> 0 | I72: =(I71+Projection!J70)*(1+G72) -> 1134473 | J72: =I72/PRODUCT(1+H$7:H72) -> 1134473 | K72: =Inputs!B17 -> 0.065 | L72: =Inputs!B16 -> 0 | M72: =(M71+Projection!J70)*(1+K72) -> 2220617.4 | N72: =M72/PRODUCT(1+L$7:L72) -> 2220617.4 | O72: =Inputs!B17 -> 0.065 | P72: =Inputs!B16 -> 0 | Q72: =(Q71+Projection!J70)*(1+O72) -> 1131878.3 | R72: =Q72/PRODUCT(1+P$7:P72) -> 1131878.3
A73: 66 | B73: 66 | C73: =Inputs!B17 -> 0.065 | D73: =Inputs!B16 -> 0 | E73: =(E72+Projection!J71)*(1+C73) -> 2246633.8 | F73: =E73/(1+Inputs!B16)^(66+1) -> 2246633.8 | G73: =Inputs!B17 -> 0.065 | H73: =Inputs!B16 -> 0 | I73: =(I72+Projection!J71)*(1+G73) -> 1212483.7 | J73: =I73/PRODUCT(1+H$7:H73) -> 1212483.7 | K73: =Inputs!B17 -> 0.065 | L73: =Inputs!B16 -> 0 | M73: =(M72+Projection!J71)*(1+K73) -> 2369227.5 | N73: =M73/PRODUCT(1+L$7:L73) -> 2369227.5 | O73: =Inputs!B17 -> 0.065 | P73: =Inputs!B16 -> 0 | Q73: =(Q72+Projection!J71)*(1+O73) -> 1209720.3 | R73: =Q73/PRODUCT(1+P$7:P73) -> 1209720.3
A74: 67 | B74: 67 | C74: =Inputs!B17 -> 0.065 | D74: =Inputs!B16 -> 0 | E74: =(E73+Projection!J72)*(1+C74) -> 2396998.7 | F74: =E74/(1+Inputs!B16)^(67+1) -> 2396998.7 | G74: =Inputs!B17 -> 0.065 | H74: =Inputs!B16 -> 0 | I74: =(I73+Projection!J72)*(1+G74) -> 1295628.8 | J74: =I74/PRODUCT(1+H$7:H74) -> 1295628.8 | K74: =Inputs!B17 -> 0.065 | L74: =Inputs!B16 -> 0 | M74: =(M73+Projection!J72)*(1+K74) -> 2527560.9 | N74: =M74/PRODUCT(1+L$7:L74) -> 2527560.9 | O74: =Inputs!B17 -> 0.065 | P74: =Inputs!B16 -> 0 | Q74: =(Q73+Projection!J72)*(1+O74) -> 1292685.8 | R74: =Q74/PRODUCT(1+P$7:P74) -> 1292685.8
A75: 68 | B75: 68 | C75: =Inputs!B17 -> 0.065 | D75: =Inputs!B16 -> 0 | E75: =(E74+Projection!J73)*(1+C75) -> 2557202 | F75: =E75/(1+Inputs!B16)^(68+1) -> 2557202 | G75: =Inputs!B17 -> 0.065 | H75: =Inputs!B16 -> 0 | I75: =(I74+Projection!J73)*(1+G75) -> 1384243 | J75: =I75/PRODUCT(1+H$7:H75) -> 1384243 | K75: =Inputs!B17 -> 0.065 | L75: =Inputs!B16 -> 0 | M75: =(M74+Projection!J73)*(1+K75) -> 2696250.8 | N75: =M75/PRODUCT(1+L$7:L75) -> 2696250.8 | O75: =Inputs!B17 -> 0.065 | P75: =Inputs!B16 -> 0 | Q75: =(Q74+Projection!J73)*(1+O75) -> 1381108.7 | R75: =Q75/PRODUCT(1+P$7:P75) -> 1381108.7
A76: 69 | B76: 69 | C76: =Inputs!B17 -> 0.065 | D76: =Inputs!B16 -> 0 | E76: =(E75+Projection!J74)*(1+C76) -> 2727884.1 | F76: =E76/(1+Inputs!B16)^(69+1) -> 2727884.1 | G76: =Inputs!B17 -> 0.065 | H76: =Inputs!B16 -> 0 | I76: =(I75+Projection!J74)*(1+G76) -> 1478682.9 | J76: =I76/PRODUCT(1+H$7:H76) -> 1478682.9 | K76: =Inputs!B17 -> 0.065 | L76: =Inputs!B16 -> 0 | M76: =(M75+Projection!J74)*(1+K76) -> 2875971.1 | N76: =M76/PRODUCT(1+L$7:L76) -> 2875971.1 | O76: =Inputs!B17 -> 0.065 | P76: =Inputs!B16 -> 0 | Q76: =(Q75+Projection!J74)*(1+O76) -> 1475344.8 | R76: =Q76/PRODUCT(1+P$7:P76) -> 1475344.8
A77: 70 | B77: 70 | C77: =Inputs!B17 -> 0.065 | D77: =Inputs!B16 -> 0 | E77: =(E76+Projection!J75)*(1+C77) -> 2909727.2 | F77: =E77/(1+Inputs!B16)^(70+1) -> 2909727.2 | G77: =Inputs!B17 -> 0.065 | H77: =Inputs!B16 -> 0 | I77: =(I76+Projection!J75)*(1+G77) -> 1579327.9 | J77: =I77/PRODUCT(1+H$7:H77) -> 1579327.9 | K77: =Inputs!B17 -> 0.065 | L77: =Inputs!B16 -> 0 | M77: =(M76+Projection!J75)*(1+K77) -> 3067439.8 | N77: =M77/PRODUCT(1+L$7:L77) -> 3067439.8 | O77: =Inputs!B17 -> 0.065 | P77: =Inputs!B16 -> 0 | Q77: =(Q76+Projection!J75)*(1+O77) -> 1575772.9 | R77: =Q77/PRODUCT(1+P$7:P77) -> 1575772.9
A78: 71 | B78: 71 | C78: =Inputs!B17 -> 0.065 | D78: =Inputs!B16 -> 0 | E78: =(E77+Projection!J76)*(1+C78) -> 3103457.7 | F78: =E78/(1+Inputs!B16)^(71+1) -> 3103457.7 | G78: =Inputs!B17 -> 0.065 | H78: =Inputs!B16 -> 0 | I78: =(I77+Projection!J76)*(1+G78) -> 1686582.4 | J78: =I78/PRODUCT(1+H$7:H78) -> 1686582.4 | K78: =Inputs!B17 -> 0.065 | L78: =Inputs!B16 -> 0 | M78: =(M77+Projection!J76)*(1+K78) -> 3271421.7 | N78: =M78/PRODUCT(1+L$7:L78) -> 3271421.7 | O78: =Inputs!B17 -> 0.065 | P78: =Inputs!B16 -> 0 | Q78: =(Q77+Projection!J76)*(1+O78) -> 1682796.4 | R78: =Q78/PRODUCT(1+P$7:P78) -> 1682796.4
A79: 72 | B79: 72 | C79: =Inputs!B17 -> 0.065 | D79: =Inputs!B16 -> 0 | E79: =(E78+Projection!J77)*(1+C79) -> 3309849.4 | F79: =E79/(1+Inputs!B16)^(72+1) -> 3309849.4 | G79: =Inputs!B17 -> 0.065 | H79: =Inputs!B16 -> 0 | I79: =(I78+Projection!J77)*(1+G79) -> 1800877.2 | J79: =I79/PRODUCT(1+H$7:H79) -> 1800877.2 | K79: =Inputs!B17 -> 0.065 | L79: =Inputs!B16 -> 0 | M79: =(M78+Projection!J77)*(1+K79) -> 3488731 | N79: =M79/PRODUCT(1+L$7:L79) -> 3488731 | O79: =Inputs!B17 -> 0.065 | P79: =Inputs!B16 -> 0 | Q79: =(Q78+Projection!J77)*(1+O79) -> 1796845 | R79: =Q79/PRODUCT(1+P$7:P79) -> 1796845
A80: 73 | B80: 73 | C80: =Inputs!B17 -> 0.065 | D80: =Inputs!B16 -> 0 | E80: =(E79+Projection!J78)*(1+C80) -> 3529726.1 | F80: =E80/(1+Inputs!B16)^(73+1) -> 3529726.1 | G80: =Inputs!B17 -> 0.065 | H80: =Inputs!B16 -> 0 | I80: =(I79+Projection!J78)*(1+G80) -> 1922670.7 | J80: =I80/PRODUCT(1+H$7:H80) -> 1922670.7 | K80: =Inputs!B17 -> 0.065 | L80: =Inputs!B16 -> 0 | M80: =(M79+Projection!J78)*(1+K80) -> 3720235 | N80: =M80/PRODUCT(1+L$7:L80) -> 3720235 | O80: =Inputs!B17 -> 0.065 | P80: =Inputs!B16 -> 0 | Q80: =(Q79+Projection!J78)*(1+O80) -> 1918376.5 | R80: =Q80/PRODUCT(1+P$7:P80) -> 1918376.5
A81: 74 | B81: 74 | C81: =Inputs!B17 -> 0.065 | D81: =Inputs!B16 -> 0 | E81: =(E80+Projection!J79)*(1+C81) -> 3763965.5 | F81: =E81/(1+Inputs!B16)^(74+1) -> 3763965.5 | G81: =Inputs!B17 -> 0.065 | H81: =Inputs!B16 -> 0 | I81: =(I80+Projection!J79)*(1+G81) -> 2052451.6 | J81: =I81/PRODUCT(1+H$7:H81) -> 2052451.6 | K81: =Inputs!B17 -> 0.065 | L81: =Inputs!B16 -> 0 | M81: =(M80+Projection!J79)*(1+K81) -> 3966857.5 | N81: =M81/PRODUCT(1+L$7:L81) -> 3966857.5 | O81: =Inputs!B17 -> 0.065 | P81: =Inputs!B16 -> 0 | Q81: =(Q80+Projection!J79)*(1+O81) -> 2047878.2 | R81: =Q81/PRODUCT(1+P$7:P81) -> 2047878.2
A82: 75 | B82: 75 | C82: =Inputs!B17 -> 0.065 | D82: =Inputs!B16 -> 0 | E82: =(E81+Projection!J80)*(1+C82) -> 4013502.3 | F82: =E82/(1+Inputs!B16)^(75+1) -> 4013502.3 | G82: =Inputs!B17 -> 0.065 | H82: =Inputs!B16 -> 0 | I82: =(I81+Projection!J80)*(1+G82) -> 2190739.9 | J82: =I82/PRODUCT(1+H$7:H82) -> 2190739.9 | K82: =Inputs!B17 -> 0.065 | L82: =Inputs!B16 -> 0 | M82: =(M81+Projection!J80)*(1+K82) -> 4229582.2 | N82: =M82/PRODUCT(1+L$7:L82) -> 4229582.2 | O82: =Inputs!B17 -> 0.065 | P82: =Inputs!B16 -> 0 | Q82: =(Q81+Projection!J80)*(1+O82) -> 2185869.2 | R82: =Q82/PRODUCT(1+P$7:P82) -> 2185869.2
A83: 76 | B83: 76 | C83: =Inputs!B17 -> 0.065 | D83: =Inputs!B16 -> 0 | E83: =(E82+Projection!J81)*(1+C83) -> 4279331.7 | F83: =E83/(1+Inputs!B16)^(76+1) -> 4279331.7 | G83: =Inputs!B17 -> 0.065 | H83: =Inputs!B16 -> 0 | I83: =(I82+Projection!J81)*(1+G83) -> 2338089.8 | J83: =I83/PRODUCT(1+H$7:H83) -> 2338089.8 | K83: =Inputs!B17 -> 0.065 | L83: =Inputs!B16 -> 0 | M83: =(M82+Projection!J81)*(1+K83) -> 4509456.9 | N83: =M83/PRODUCT(1+L$7:L83) -> 4509456.9 | O83: =Inputs!B17 -> 0.065 | P83: =Inputs!B16 -> 0 | Q83: =(Q82+Projection!J81)*(1+O83) -> 2332902.5 | R83: =Q83/PRODUCT(1+P$7:P83) -> 2332902.5
A84: 77 | B84: 77 | C84: =Inputs!B17 -> 0.065 | D84: =Inputs!B16 -> 0 | E84: =(E83+Projection!J82)*(1+C84) -> 4562514 | F84: =E84/(1+Inputs!B16)^(77+1) -> 4562514 | G84: =Inputs!B17 -> 0.065 | H84: =Inputs!B16 -> 0 | I84: =(I83+Projection!J82)*(1+G84) -> 2495091.4 | J84: =I84/PRODUCT(1+H$7:H84) -> 2495091.4 | K84: =Inputs!B17 -> 0.065 | L84: =Inputs!B16 -> 0 | M84: =(M83+Projection!J82)*(1+K84) -> 4807597.3 | N84: =M84/PRODUCT(1+L$7:L84) -> 4807597.3 | O84: =Inputs!B17 -> 0.065 | P84: =Inputs!B16 -> 0 | Q84: =(Q83+Projection!J82)*(1+O84) -> 2489566.9 | R84: =Q84/PRODUCT(1+P$7:P84) -> 2489566.9
A85: 78 | B85: 78 | C85: =Inputs!B17 -> 0.065 | D85: =Inputs!B16 -> 0 | E85: =(E84+Projection!J83)*(1+C85) -> 4864178.1 | F85: =E85/(1+Inputs!B16)^(78+1) -> 4864178.1 | G85: =Inputs!B17 -> 0.065 | H85: =Inputs!B16 -> 0 | I85: =(I84+Projection!J83)*(1+G85) -> 2662373 | J85: =I85/PRODUCT(1+H$7:H85) -> 2662373 | K85: =Inputs!B17 -> 0.065 | L85: =Inputs!B16 -> 0 | M85: =(M84+Projection!J83)*(1+K85) -> 5125191.9 | N85: =M85/PRODUCT(1+L$7:L85) -> 5125191.9 | O85: =Inputs!B17 -> 0.065 | P85: =Inputs!B16 -> 0 | Q85: =(Q84+Projection!J83)*(1+O85) -> 2656489.5 | R85: =Q85/PRODUCT(1+P$7:P85) -> 2656489.5
A86: 79 | B86: 79 | C86: =Inputs!B17 -> 0.065 | D86: =Inputs!B16 -> 0 | E86: =(E85+Projection!J84)*(1+C86) -> 5185526.6 | F86: =E86/(1+Inputs!B16)^(79+1) -> 5185526.6 | G86: =Inputs!B17 -> 0.065 | H86: =Inputs!B16 -> 0 | I86: =(I85+Projection!J84)*(1+G86) -> 2840604.1 | J86: =I86/PRODUCT(1+H$7:H86) -> 2840604.1 | K86: =Inputs!B17 -> 0.065 | L86: =Inputs!B16 -> 0 | M86: =(M85+Projection!J84)*(1+K86) -> 5463506.2 | N86: =M86/PRODUCT(1+L$7:L86) -> 5463506.2 | O86: =Inputs!B17 -> 0.065 | P86: =Inputs!B16 -> 0 | Q86: =(Q85+Projection!J84)*(1+O86) -> 2834338.2 | R86: =Q86/PRODUCT(1+P$7:P86) -> 2834338.2
A87: 80 | B87: 80 | C87: =Inputs!B17 -> 0.065 | D87: =Inputs!B16 -> 0 | E87: =(E86+Projection!J85)*(1+C87) -> 5527839.9 | F87: =E87/(1+Inputs!B16)^(80+1) -> 5527839.9 | G87: =Inputs!B17 -> 0.065 | H87: =Inputs!B16 -> 0 | I87: =(I86+Projection!J85)*(1+G87) -> 3030497.5 | J87: =I87/PRODUCT(1+H$7:H87) -> 3030497.5 | K87: =Inputs!B17 -> 0.065 | L87: =Inputs!B16 -> 0 | M87: =(M86+Projection!J85)*(1+K87) -> 5823888.2 | N87: =M87/PRODUCT(1+L$7:L87) -> 5823888.2 | O87: =Inputs!B17 -> 0.065 | P87: =Inputs!B16 -> 0 | Q87: =(Q86+Projection!J85)*(1+O87) -> 3023824.3 | R87: =Q87/PRODUCT(1+P$7:P87) -> 3023824.3
A89: Headline outputs at horizon
A90: Scenario | B90: Stable Floor at horizon (real $) | C90: 4% withdrawal income | D90: vs. smooth baseline | E90: × median American
A91: Smooth baseline (no shocks) | B91: =INDEX(F7:F87,MATCH(Inputs!B23,A7:A87,0)) -> 2105506 | C91: =B91*Inputs!B24 -> 84220.239 | D91: (reference) | E91: =B91/87571 -> 24.043416
A92: Great Depression (age 25-40) | B92: =INDEX(J7:J87,MATCH(Inputs!B23,A7:A87,0)) -> 1134473 | C92: =B92*Inputs!B24 -> 45378.92 | D92: =(B92-B91)/B91 -> -0.46118747 | E92: =B92/87571 -> 12.954894
A93: 1970s Stagflation (age 30-46) | B93: =INDEX(N7:N87,MATCH(Inputs!B23,A7:A87,0)) -> 2220617.4 | C93: =B93*Inputs!B24 -> 88824.696 | D93: =(B93-B91)/B91 -> 0.054671621 | E93: =B93/87571 -> 25.357908
A94: 2000s Lost Decade (age 35-44) | B94: =INDEX(R7:R87,MATCH(Inputs!B23,A7:A87,0)) -> 1131878.3 | C94: =B94*Inputs!B24 -> 45275.131 | D94: =(B94-B91)/B91 -> -0.46241982 | E94: =B94/87571 -> 12.925264
A97: Sources for historical sequences
A98: Robert Shiller's annual real returns dataset (Yale University, 1871-present): http://www.econ.yale.edu/~shiller/data.htm
A99: BLS Consumer Price Index Historical Tables (annual averages, 1913-present)
A100: Great Depression sequence (1929-1944): real annualized return ≈ +1.5% with severe year-to-year variation; CPI deflation 1929-1933 then mild inflation
A101: 1970s Stagflation sequence (1966-1982): real annualized return ≈ -1.0%; CPI annualized ≈ 7.5% with peaks above 13%
A102: 2000s Lost Decade sequence (2000-2009): real annualized return ≈ -3.0% (dot-com crash + GFC); CPI annualized ≈ 2.5%

Sheet Mode Presets
A1: Mode reference values from the paper
A2: Copy these into the Inputs sheet to replay any of the three constitutional Modes.
A3: What each Mode optimizes
A4: Parameter | B4: Mode A — Maximum wealth (deflation) | C4: Mode B — Stable prices (neutral) | D4: Mode C — Monthly dividend (inflation) | E4: Notes
A5: K1 — Citizenship | B5: 2.5% | C5: 2.5% | D5: 2.5% | E5: Identical across modes — anchor the citizenship endowment.
A6: K2 — Growth | B6: 12.5% | C6: 84% | D6: 12.5% | E6: Mode B raises K2 share to absorb full real-growth issuance.
A7: K3 — Dividend | B7: 0% | C7: 0% | D7: ~4.0% | E7: Mode C only. Calibrated by price-level path targeting.
A8: CPI target | B8: -1.6% | C8: 0% | D8: +2.0% | E8: The defining macro outcome of each mode.
A9: Stable Floor at 65 (real) | B9: $1.7M | C9: $2.6M | D9: $145K | E9: Mode A wins on long-run wealth; Mode C trades it for dividends.
A10: Annual real income at 65 | B10: $68K | C10: $105K | D10: $5.8K + K3 | E10: 4% withdrawal rate, plus ongoing K3 in Mode C.
A11: K3 monthly dividend, yr 1 | B11: $0 | C11: $0 | D11: $208 | E11: Per citizen, rises with M2 over time.
A12: Total issuance / M2 | B12: ~0.35% | C12: ~2.5% | D12: ~4.1% | E12: Annual issuance as fraction of money supply.
A13: Constitutional change | B13: Tier 2: 67% supermajority + 90-day deliberation | E13: Modes do NOT auto-rotate. Selection is a constitutional act.
A15: Mode philosophy
A16: Mode A | B16: Maximum lifetime wealth via gentle deflation. No monthly dividend. K2 contracts to ~12.5% so most of real growth flows to falling prices rather than expanding M2. The Stable Floor compounds aggressively because purchasing power rises over time. Best for retirement-focused societies.
A17: Mode B | B17: Price stability. K2 expanded to ~84% so circulating money matches real growth exactly — no monetary inflation, no monetary deflation. Highest possible Stable Floor wealth without dividend. Default neutral mode.
A18: Mode C | B18: Monthly citizen dividend at the cost of lower locked wealth. K3 activates (~4% of M2) and is calibrated by price-level path targeting to hit ~2% inflation. Citizens get ~$208/month at launch (rising over time) plus a smaller Stable Floor.

Sheet How It Works
A1: Formula reference and assumptions — Interactive Model Builder
A3: Architecture
A4: Two pools | B4: Circulating money (M2) and the Citizen Equity Stake (Stable Floor). They intersect only at K1/K2 issuance and at retirement withdrawals.
A5: Three channels | B5: K1 fires once per new citizen. K2 fires every year. K3 fires monthly (active in Mode C).
A7: K1 formula | B7: K1 total = K1_share × (GDP / population) × births_this_year
A8: K2 formula | B8: K2 total = K2_share × (GDP × real_growth_rate)
A9: K3 formula | B9: K3 total = K3_share × M2 (paper uses price-level path targeting; this engine uses a flat % of M2 as the simplified equivalent)
A11: Stable Floor | B11: For our representative cohort (born at t=0): floor compounds at the equity return rate. K1 is deposited once at birth; K2 is deposited every year. Both lock until retirement.
A12: Real values | B12: CPI index starts at 1.0 and grows at the CPI inflation rate. Real value = nominal / CPI index.
A13: K3 distribution | B13: K3 is unlocked, immediately spendable, deposited monthly into citizen transaction accounts.
A15: Simplifications | B15: This engine is a single-cohort projection with constant rates. The full paper models stochastic returns, mode transitions, sequence-of-returns risk, and emergency tools. Use this for intuition, not policy calibration.
A16: Equity return | B16: Treated as nominal in this model. If you want real returns, set CPI=0 and the equity return is automatically real.
A17: Births formula | B17: Births = pop × pop_growth_rate. Real demographics are more complex; this is a proxy.
A18: Mode C K3 calibration | B18: The paper calibrates K3 dynamically to close the cumulative CPI gap. Setting K3 to a flat ~4% of M2 reproduces the launch-year value but not the dynamic behavior.
... A27: Stress Test sheet | B27: Year-by-year simulation of the Stable Floor under three real historical adverse sequences (Great Depression 1929-1944, 1970s Stagflation 1966-1982, 2000s Lost Decade 2000-2009) plus the smooth baseline. Returns and CPI for stress periods come from Robert Shiller's dataset and BLS historical CPI. Headline outputs at top show Stable Floor at horizon, 4% withdrawal income, percent change vs. baseline, and the multiple of $87,571 (median American 401k at 55-64). Adjust your equity return and CPI inputs on the Inputs sheet to see how different baseline assumptions change the stress test outcomes.
